{"ticker":{"7681":"AAOI","7361":"AAOI","8295":"AAOI","8243":"AAOI","8316":"AAOI","8661":"AAOI","8742":"AAOI","8700":"AAOI","8673":"AAOI","9324":"AAOI","15813":"AAOI","15830":"AAOI","15751":"AAOI","15804":"AAOI","15810":"AAOI","16926":"AAOI","26150":"AAOI"},"date":{"7681":"2025-08-15 00:00:00.000000","7361":"2025-08-15 00:00:00.000000","8295":"2025-08-14 00:00:00.000000","8243":"2025-08-14 00:00:00.000000","8316":"2025-08-14 00:00:00.000000","8661":"2025-08-13 00:00:00.000000","8742":"2025-08-13 00:00:00.000000","8700":"2025-08-13 00:00:00.000000","8673":"2025-08-13 00:00:00.000000","9324":"2025-08-12 00:00:00.000000","15813":"2025-07-22 00:00:00.000000","15830":"2025-07-22 00:00:00.000000","15751":"2025-07-22 00:00:00.000000","15804":"2025-07-22 00:00:00.000000","15810":"2025-07-22 00:00:00.000000","16926":"2025-07-16 00:00:00.000000","26150":"2025-06-16 00:00:00.000000"},"transactionvalue":{"7681":44680.0,"7361":268440.0,"8295":99739.0,"8243":174057.0,"8316":85600.0,"8661":358313.0,"8742":171825.0,"8700":273002.0,"8673":320100.0,"9324":150410.0,"15813":190044.0,"15830":127854.0,"15751":626988.0,"15804":213390.0,"15810":197581.0,"16926":82377.0,"26150":32090.0},"transactionshares":{"7681":-2000,"7361":-12000,"8295":4609,"8243":8075,"8316":4000,"8661":-15784,"8742":7500,"8700":12100,"8673":14000,"9324":6500,"15813":-6732,"15830":-4529,"15751":-22210,"15804":-7559,"15810":-6999,"16926":-3000,"26150":-2000},"securitytitle":{"7681":"Common Stock .001 par value","7361":"Common Stock .001 par value","8295":"Common Stock .001 par value","8243":"Common Stock .001 par value","8316":"Common Stock .001 par value","8661":"Common Stock .001 par value","8742":"Common Stock .001 par value","8700":"Common Stock .001 par value","8673":"Common Stock .001 par value","9324":"Common Stock .001 par value","15813":"Common Stock .001 par value","15830":"Common Stock .001 par value","15751":"Common Stock .001 par value","15804":"Common Stock .001 par value","15810":"Common Stock .001 par value","16926":"Common Stock .001 par value","26150":"Common Stock .001 par value"},"transactioncode":{"7681":"S","7361":"S","8295":"P","8243":"P","8316":"P","8661":"S","8742":"P","8700":"P","8673":"P","9324":"P","15813":"F","15830":"F","15751":"F","15804":"F","15810":"F","16926":"S","26150":"S"},"securityadcode":{"7681":"ND","7361":"ND","8295":null,"8243":null,"8316":null,"8661":"ND","8742":null,"8700":null,"8673":null,"9324":null,"15813":"ND","15830":"ND","15751":"ND","15804":"ND","15810":"ND","16926":"ND","26150":"ND"},"issuername":{"7681":"APPLIED OPTOELECTRONICS I","7361":"APPLIED OPTOELECTRONICS I","8295":"APPLIED OPTOELECTRONICS I","8243":"APPLIED OPTOELECTRONICS I","8316":"APPLIED OPTOELECTRONICS I","8661":"APPLIED OPTOELECTRONICS I","8742":"APPLIED OPTOELECTRONICS I","8700":"APPLIED OPTOELECTRONICS I","8673":"APPLIED OPTOELECTRONICS I","9324":"APPLIED OPTOELECTRONICS I","15813":"APPLIED OPTOELECTRONICS I","15830":"APPLIED OPTOELECTRONICS I","15751":"APPLIED OPTOELECTRONICS I","15804":"APPLIED OPTOELECTRONICS I","15810":"APPLIED OPTOELECTRONICS I","16926":"APPLIED OPTOELECTRONICS I","26150":"APPLIED OPTOELECTRONICS I"},"ownername":{"7681":"KUO DAVID C","7361":"MURRY STEFAN J","8295":"LIN CHEWEI","8243":"LIN CHIHHSIANG THOMPSON","8316":"YEH WILLIAM H","8661":"CHANG HUNGLUN FRED","8742":"CHEN MINCHU MIKE","8700":"LIN CHIHHSIANG THOMPSON","8673":"YEH WILLIAM H","9324":"LIN CHIHHSIANG THOMPSON","15813":"CHANG HUNGLUN FRED","15830":"KUO DAVID C","15751":"LIN CHIHHSIANG THOMPSON","15804":"MURRY STEFAN J","15810":"YEH SHUHUA JOSHUA","16926":"MURRY STEFAN J","26150":"MURRY STEFAN J"},"officertitle":{"7681":"Senior Vice President and Chief Legal Officer","7361":"Chief Financial Officer","8295":null,"8243":"President and CEO","8316":null,"8661":" Senior Vice President and North America General Manager","8742":null,"8700":"President and CEO","8673":null,"9324":"President and CEO","15813":" Senior Vice President and North America General Manager.","15830":"Senior Vice President and Chief Legal Officer","15751":"President and CEO","15804":"Chief Financial Officer","15810":"Senior Vice President and Asia General Manager.","16926":"Chief Financial Officer","26150":"Chief Financial Officer"},"isofficer":{"7681":"Y","7361":"Y","8295":"N","8243":"Y","8316":"N","8661":"Y","8742":"N","8700":"Y","8673":"N","9324":"Y","15813":"Y","15830":"Y","15751":"Y","15804":"Y","15810":"Y","16926":"Y","26150":"Y"},"isdirector":{"7681":"N","7361":"N","8295":"Y","8243":"Y","8316":"Y","8661":"N","8742":"Y","8700":"Y","8673":"Y","9324":"Y","15813":"N","15830":"N","15751":"Y","15804":"N","15810":"N","16926":"N","26150":"N"},"istenpercentowner":{"7681":"N","7361":"N","8295":"N","8243":"N","8316":"N","8661":"N","8742":"N","8700":"N","8673":"N","9324":"N","15813":"N","15830":"N","15751":"N","15804":"N","15810":"N","16926":"N","26150":"N"},"transactionpricepershare":{"7681":22.34,"7361":22.37,"8295":21.64,"8243":21.49,"8316":21.4,"8661":22.7,"8742":22.91,"8700":22.59,"8673":22.95,"9324":23.14,"15813":28.23,"15830":28.23,"15751":28.23,"15804":28.23,"15810":28.23,"16926":27.46,"26150":16.05}}