{"ticker":{"225":"ABTC","13530":"ABTC","13660":"ABTC","23337":"ABTC","23338":"ABTC","23339":"ABTC"},"date":{"225":"2025-09-03 00:00:00.000000","13530":"2025-07-31 00:00:00.000000","13660":"2025-07-31 00:00:00.000000","23337":"2025-06-24 00:00:00.000000","23338":"2025-06-24 00:00:00.000000","23339":"2025-06-24 00:00:00.000000"},"transactionvalue":{"225":20189719.0,"13530":153111.0,"13660":25817.0,"23337":1135416.0,"23338":1135302.0,"23339":1135302.0},"transactionshares":{"225":-2534490,"13530":-149086,"13660":-25486,"23337":-1145728,"23338":5530198,"23339":-5530198},"securitytitle":{"225":"Class A Common Stock","13530":"Common Stock","13660":"Common Stock","23337":"Common Stock","23338":"Common Stock","23339":"Warrant right to buy"},"transactioncode":{"225":"S","13530":"F","13660":"F","23337":"F","23338":"M","23339":"M"},"securityadcode":{"225":"ND","13530":"ND","13660":"ND","23337":"ND","23338":null,"23339":"DD"},"issuername":{"225":"AMERICAN BITCOIN CORP","13530":"AMERICAN BITCOIN CORP","13660":"AMERICAN BITCOIN CORP","23337":"AMERICAN BITCOIN CORP","23338":"AMERICAN BITCOIN CORP","23339":"AMERICAN BITCOIN CORP"},"ownername":{"225":"ANCHORAGE LENDING CA LLC","13530":"GUTTERMAN STEVEN D","13660":"SALZMAN SIMEON","23337":"ANCHORAGE LENDING CA LLC","23338":"ANCHORAGE LENDING CA LLC","23339":"ANCHORAGE LENDING CA LLC"},"officertitle":{"225":null,"13530":"Chief Executive Officer","13660":"Chief Financial Officer","23337":null,"23338":null,"23339":null},"isofficer":{"225":"N","13530":"Y","13660":"Y","23337":"N","23338":"N","23339":"N"},"isdirector":{"225":"Y","13530":"Y","13660":"N","23337":"Y","23338":"Y","23339":"Y"},"istenpercentowner":{"225":"Y","13530":"N","13660":"N","23337":"Y","23338":"Y","23339":"Y"},"transactionpricepershare":{"225":8.34,"13530":1.03,"13660":1.01,"23337":0.99,"23338":0.28,"23339":0.28}}