{"index":{"413414":413414,"417897":417897,"420012":420012,"421564":421564,"424304":424304,"424624":424624,"428207":428207,"433706":433706,"434476":434476,"437977":437977,"441712":441712,"445018":445018,"445944":445944,"447729":447729,"450769":450769,"452756":452756,"452938":452938,"454861":454861,"457762":457762,"459771":459771,"462000":462000,"467443":467443,"469692":469692,"472132":472132,"476122":476122,"481752":481752,"483568":483568,"484202":484202,"485550":485550,"485707":485707,"486613":486613,"487631":487631,"491823":491823,"494104":494104,"495511":495511,"496353":496353,"510009":510009,"510032":510032,"511502":511502,"512239":512239,"518498":518498,"519869":519869,"520681":520681,"521696":521696,"523367":523367,"524604":524604,"531050":531050,"535862":535862,"558179":558179,"558342":558342,"559362":559362,"560299":560299,"563060":563060,"565564":565564,"565763":565763,"566605":566605,"584635":584635,"585955":585955,"600799":600799,"605868":605868,"606079":606079,"616782":616782,"632106":632106,"643690":643690,"651165":651165,"663463":663463,"675973":675973,"686139":686139,"718833":718833,"736214":736214,"786454":786454,"852203":852203,"862140":862140,"867986":867986,"871970":871970,"876199":876199,"879512":879512,"884431":884431,"890432":890432,"899376":899376,"900465":900465,"926528":926528,"937852":937852,"940682":940682,"1081830":1081830,"1107961":1107961,"1122969":1122969,"1212437":1212437,"1255697":1255697,"1345835":1345835,"1411669":1411669,"1483303":1483303,"1513835":1513835},"ticker":{"413414":"MSFT","417897":"NVDA","420012":"RTX","421564":"JPM","424304":"BK","424624":"CSCO","428207":"AMZN","433706":"KMI","434476":"KLAC","437977":"V","441712":"MCK","445018":"GOOGL","445944":"MOS","447729":"BTI","450769":"WRB","452756":"ALL","452938":"NEE","454861":"UL","457762":"JCI","459771":"MU","462000":"AAPL","467443":"MET","469692":"PNW","472132":"MCD","476122":"CHKP","481752":"EOG","483568":"CMI","484202":"QCOM","485550":"CVX","485707":"MSM","486613":"LMT","487631":"MDT","491823":"VZ","494104":"LOW","495511":"GPC","496353":"AMGN","510009":"XLK","510032":"JNJ","511502":"KVUE","512239":"ABT","518498":"EFX","519869":"O","520681":"TAP","521696":"DD","523367":"BP","524604":"CMCSA","531050":"CSX","535862":"MRK","558179":"B","558342":"NUE","559362":"LEN","560299":"CVS","563060":"PEP","565564":"ADBE","565763":"ADM","566605":"EMN","584635":"SPDW","585955":"UPS","600799":"XLI","605868":"XLF","606079":"KHC","616782":"XLY","632106":"XLP","643690":"TGT","651165":"XLV","663463":"XLC","675973":"XLU","686139":"SPLG","718833":"DOW","736214":"XLB","786454":"XLE","852203":"BSCU","862140":"BSCT","867986":"BSCV","871970":"BSCS","876199":"BSCR","879512":"KO","884431":"BSCW","890432":"SDY","899376":"BSCQ","900465":"BSCX","926528":"BSCY","937852":"BSCP","940682":"SPMD","1081830":"SPY","1107961":"SPSM","1122969":"PGX","1212437":"QQQ","1255697":"SFBS","1345835":"VOO","1411669":"VIG","1483303":"VEU","1513835":"BRK.B"},"investorname":{"413414":"BUTENSKY COHEN FINANCIAL SECURITY INC","417897":"BUTENSKY COHEN FINANCIAL SECURITY INC","420012":"BUTENSKY COHEN FINANCIAL SECURITY INC","421564":"BUTENSKY COHEN FINANCIAL SECURITY INC","424304":"BUTENSKY COHEN FINANCIAL SECURITY INC","424624":"BUTENSKY COHEN FINANCIAL SECURITY INC","428207":"BUTENSKY COHEN FINANCIAL SECURITY INC","433706":"BUTENSKY COHEN FINANCIAL SECURITY INC","434476":"BUTENSKY COHEN FINANCIAL SECURITY INC","437977":"BUTENSKY COHEN FINANCIAL SECURITY INC","441712":"BUTENSKY COHEN FINANCIAL SECURITY INC","445018":"BUTENSKY COHEN FINANCIAL SECURITY INC","445944":"BUTENSKY COHEN FINANCIAL SECURITY INC","447729":"BUTENSKY COHEN FINANCIAL SECURITY INC","450769":"BUTENSKY COHEN FINANCIAL SECURITY INC","452756":"BUTENSKY COHEN FINANCIAL SECURITY INC","452938":"BUTENSKY COHEN FINANCIAL SECURITY INC","454861":"BUTENSKY COHEN FINANCIAL SECURITY INC","457762":"BUTENSKY COHEN FINANCIAL SECURITY INC","459771":"BUTENSKY COHEN FINANCIAL SECURITY INC","462000":"BUTENSKY COHEN FINANCIAL SECURITY INC","467443":"BUTENSKY COHEN FINANCIAL SECURITY INC","469692":"BUTENSKY COHEN FINANCIAL SECURITY INC","472132":"BUTENSKY COHEN FINANCIAL SECURITY INC","476122":"BUTENSKY COHEN FINANCIAL SECURITY INC","481752":"BUTENSKY COHEN FINANCIAL SECURITY INC","483568":"BUTENSKY COHEN FINANCIAL SECURITY INC","484202":"BUTENSKY COHEN FINANCIAL SECURITY INC","485550":"BUTENSKY COHEN FINANCIAL SECURITY INC","485707":"BUTENSKY COHEN FINANCIAL SECURITY INC","486613":"BUTENSKY COHEN FINANCIAL SECURITY INC","487631":"BUTENSKY COHEN FINANCIAL SECURITY INC","491823":"BUTENSKY COHEN FINANCIAL SECURITY INC","494104":"BUTENSKY COHEN FINANCIAL SECURITY INC","495511":"BUTENSKY COHEN FINANCIAL SECURITY INC","496353":"BUTENSKY COHEN FINANCIAL SECURITY INC","510009":"BUTENSKY COHEN FINANCIAL SECURITY INC","510032":"BUTENSKY COHEN FINANCIAL SECURITY INC","511502":"BUTENSKY COHEN FINANCIAL SECURITY INC","512239":"BUTENSKY COHEN FINANCIAL SECURITY INC","518498":"BUTENSKY COHEN FINANCIAL SECURITY INC","519869":"BUTENSKY COHEN FINANCIAL SECURITY INC","520681":"BUTENSKY COHEN FINANCIAL SECURITY INC","521696":"BUTENSKY COHEN FINANCIAL SECURITY INC","523367":"BUTENSKY COHEN FINANCIAL SECURITY INC","524604":"BUTENSKY COHEN FINANCIAL SECURITY INC","531050":"BUTENSKY COHEN FINANCIAL SECURITY INC","535862":"BUTENSKY COHEN FINANCIAL SECURITY INC","558179":"BUTENSKY COHEN FINANCIAL SECURITY INC","558342":"BUTENSKY COHEN FINANCIAL SECURITY INC","559362":"BUTENSKY COHEN FINANCIAL SECURITY INC","560299":"BUTENSKY COHEN FINANCIAL SECURITY INC","563060":"BUTENSKY COHEN FINANCIAL SECURITY INC","565564":"BUTENSKY COHEN FINANCIAL SECURITY INC","565763":"BUTENSKY COHEN FINANCIAL SECURITY INC","566605":"BUTENSKY COHEN FINANCIAL SECURITY INC","584635":"BUTENSKY COHEN FINANCIAL SECURITY INC","585955":"BUTENSKY COHEN FINANCIAL SECURITY INC","600799":"BUTENSKY COHEN FINANCIAL SECURITY INC","605868":"BUTENSKY COHEN FINANCIAL SECURITY INC","606079":"BUTENSKY COHEN FINANCIAL SECURITY INC","616782":"BUTENSKY COHEN FINANCIAL SECURITY INC","632106":"BUTENSKY COHEN FINANCIAL SECURITY INC","643690":"BUTENSKY COHEN FINANCIAL SECURITY INC","651165":"BUTENSKY COHEN FINANCIAL SECURITY INC","663463":"BUTENSKY COHEN FINANCIAL SECURITY INC","675973":"BUTENSKY COHEN FINANCIAL SECURITY INC","686139":"BUTENSKY COHEN FINANCIAL SECURITY INC","718833":"BUTENSKY COHEN FINANCIAL SECURITY INC","736214":"BUTENSKY COHEN FINANCIAL SECURITY INC","786454":"BUTENSKY COHEN FINANCIAL SECURITY INC","852203":"BUTENSKY COHEN FINANCIAL SECURITY INC","862140":"BUTENSKY COHEN FINANCIAL SECURITY INC","867986":"BUTENSKY COHEN FINANCIAL SECURITY INC","871970":"BUTENSKY COHEN FINANCIAL SECURITY INC","876199":"BUTENSKY COHEN FINANCIAL SECURITY INC","879512":"BUTENSKY COHEN FINANCIAL SECURITY INC","884431":"BUTENSKY COHEN FINANCIAL SECURITY INC","890432":"BUTENSKY COHEN FINANCIAL SECURITY INC","899376":"BUTENSKY COHEN FINANCIAL SECURITY INC","900465":"BUTENSKY COHEN FINANCIAL SECURITY INC","926528":"BUTENSKY COHEN FINANCIAL SECURITY INC","937852":"BUTENSKY COHEN FINANCIAL SECURITY INC","940682":"BUTENSKY COHEN FINANCIAL SECURITY INC","1081830":"BUTENSKY COHEN FINANCIAL SECURITY INC","1107961":"BUTENSKY COHEN FINANCIAL SECURITY INC","1122969":"BUTENSKY COHEN FINANCIAL SECURITY INC","1212437":"BUTENSKY COHEN FINANCIAL SECURITY INC","1255697":"BUTENSKY COHEN FINANCIAL SECURITY INC","1345835":"BUTENSKY COHEN FINANCIAL SECURITY INC","1411669":"BUTENSKY COHEN FINANCIAL SECURITY INC","1483303":"BUTENSKY COHEN FINANCIAL SECURITY INC","1513835":"BUTENSKY COHEN FINANCIAL SECURITY INC"},"securitytype":{"413414":"SHR","417897":"SHR","420012":"SHR","421564":"SHR","424304":"SHR","424624":"SHR","428207":"SHR","433706":"SHR","434476":"SHR","437977":"SHR","441712":"SHR","445018":"SHR","445944":"SHR","447729":"SHR","450769":"SHR","452756":"SHR","452938":"SHR","454861":"SHR","457762":"SHR","459771":"SHR","462000":"SHR","467443":"SHR","469692":"SHR","472132":"SHR","476122":"SHR","481752":"SHR","483568":"SHR","484202":"SHR","485550":"SHR","485707":"SHR","486613":"SHR","487631":"SHR","491823":"SHR","494104":"SHR","495511":"SHR","496353":"SHR","510009":"FND","510032":"SHR","511502":"SHR","512239":"SHR","518498":"SHR","519869":"SHR","520681":"SHR","521696":"SHR","523367":"SHR","524604":"SHR","531050":"SHR","535862":"SHR","558179":"SHR","558342":"SHR","559362":"SHR","560299":"SHR","563060":"SHR","565564":"SHR","565763":"SHR","566605":"SHR","584635":"FND","585955":"SHR","600799":"FND","605868":"FND","606079":"SHR","616782":"FND","632106":"FND","643690":"SHR","651165":"FND","663463":"FND","675973":"FND","686139":"FND","718833":"SHR","736214":"FND","786454":"FND","852203":"FND","862140":"FND","867986":"FND","871970":"FND","876199":"FND","879512":"SHR","884431":"FND","890432":"FND","899376":"FND","900465":"FND","926528":"FND","937852":"FND","940682":"FND","1081830":"FND","1107961":"FND","1122969":"FND","1212437":"FND","1255697":"SHR","1345835":"FND","1411669":"FND","1483303":"FND","1513835":"SHR"},"calendardate":{"413414":"2025-06-30","417897":"2025-06-30","420012":"2025-06-30","421564":"2025-06-30","424304":"2025-06-30","424624":"2025-06-30","428207":"2025-06-30","433706":"2025-06-30","434476":"2025-06-30","437977":"2025-06-30","441712":"2025-06-30","445018":"2025-06-30","445944":"2025-06-30","447729":"2025-06-30","450769":"2025-06-30","452756":"2025-06-30","452938":"2025-06-30","454861":"2025-06-30","457762":"2025-06-30","459771":"2025-06-30","462000":"2025-06-30","467443":"2025-06-30","469692":"2025-06-30","472132":"2025-06-30","476122":"2025-06-30","481752":"2025-06-30","483568":"2025-06-30","484202":"2025-06-30","485550":"2025-06-30","485707":"2025-06-30","486613":"2025-06-30","487631":"2025-06-30","491823":"2025-06-30","494104":"2025-06-30","495511":"2025-06-30","496353":"2025-06-30","510009":"2025-06-30","510032":"2025-06-30","511502":"2025-06-30","512239":"2025-06-30","518498":"2025-06-30","519869":"2025-06-30","520681":"2025-06-30","521696":"2025-06-30","523367":"2025-06-30","524604":"2025-06-30","531050":"2025-06-30","535862":"2025-06-30","558179":"2025-06-30","558342":"2025-06-30","559362":"2025-06-30","560299":"2025-06-30","563060":"2025-06-30","565564":"2025-06-30","565763":"2025-06-30","566605":"2025-06-30","584635":"2025-06-30","585955":"2025-06-30","600799":"2025-06-30","605868":"2025-06-30","606079":"2025-06-30","616782":"2025-06-30","632106":"2025-06-30","643690":"2025-06-30","651165":"2025-06-30","663463":"2025-06-30","675973":"2025-06-30","686139":"2025-06-30","718833":"2025-06-30","736214":"2025-06-30","786454":"2025-06-30","852203":"2025-06-30","862140":"2025-06-30","867986":"2025-06-30","871970":"2025-06-30","876199":"2025-06-30","879512":"2025-06-30","884431":"2025-06-30","890432":"2025-06-30","899376":"2025-06-30","900465":"2025-06-30","926528":"2025-06-30","937852":"2025-06-30","940682":"2025-06-30","1081830":"2025-06-30","1107961":"2025-06-30","1122969":"2025-06-30","1212437":"2025-06-30","1255697":"2025-06-30","1345835":"2025-06-30","1411669":"2025-06-30","1483303":"2025-06-30","1513835":"2025-06-30"},"value":{"413414":6629666.0,"417897":6496075.0,"420012":6434080.0,"421564":6388167.0,"424304":6309094.0,"424624":6300398.0,"428207":6202814.0,"433706":6052108.0,"434476":6031913.0,"437977":5940697.0,"441712":5842293.0,"445018":5760959.0,"445944":5736626.0,"447729":5694793.0,"450769":5619280.0,"452756":5571254.0,"452938":5566859.0,"454861":5521205.0,"457762":5450520.0,"459771":5403280.0,"462000":5352170.0,"467443":5231803.0,"469692":5183892.0,"472132":5131674.0,"476122":5047819.0,"481752":4932358.0,"483568":4894815.0,"484202":4881478.0,"485550":4854571.0,"485707":4851752.0,"486613":4832866.0,"487631":4812481.0,"491823":4729152.0,"494104":4684119.0,"495511":4656970.0,"496353":4641308.0,"510009":4393422.0,"510032":4393090.0,"511502":4366877.0,"512239":4353408.0,"518498":4242515.0,"519869":4219414.0,"520681":4205903.0,"521696":4188723.0,"523367":4161351.0,"524604":4141147.0,"531050":4037622.0,"535862":3961799.0,"558179":3631945.0,"558342":3629970.0,"559362":3616283.0,"560299":3603220.0,"563060":3565608.0,"565564":3531441.0,"565763":3528677.0,"566605":3517687.0,"584635":3286280.0,"585955":3270806.0,"600799":3095265.0,"605868":3039835.0,"606079":3037368.0,"616782":2921537.0,"632106":2766013.0,"643690":2653389.0,"651165":2584665.0,"663463":2477957.0,"675973":2372630.0,"686139":2291983.0,"718833":2053242.0,"736214":1939382.0,"786454":1647350.0,"852203":1344095.0,"862140":1304755.0,"867986":1281885.0,"871970":1266712.0,"876199":1250271.0,"879512":1237979.0,"884431":1220056.0,"890432":1198541.0,"899376":1166788.0,"900465":1163159.0,"926528":1078336.0,"937852":1043141.0,"940682":1034704.0,"1081830":700642.0,"1107961":653689.0,"1122969":628389.0,"1212437":500467.0,"1255697":450333.0,"1345835":362868.0,"1411669":311303.0,"1483303":264780.0,"1513835":247743.0},"units":{"413414":13328.0,"417897":41117.0,"420012":44063.0,"421564":22035.0,"424304":69247.0,"424624":90810.0,"428207":28273.0,"433706":205854.0,"434476":6734.0,"437977":16732.0,"441712":7973.0,"445018":32690.0,"445944":157254.0,"447729":120321.0,"450769":76484.0,"452756":27675.0,"452938":80191.0,"454861":90260.0,"457762":51605.0,"459771":43840.0,"462000":26087.0,"467443":65056.0,"469692":57940.0,"472132":17564.0,"476122":22815.0,"481752":41237.0,"483568":14946.0,"484202":30651.0,"485550":33903.0,"485707":57066.0,"486613":10435.0,"487631":55208.0,"491823":109294.0,"494104":21112.0,"495511":38389.0,"496353":16623.0,"510009":17350.0,"510032":28760.0,"511502":208642.0,"512239":32008.0,"518498":16357.0,"519869":73241.0,"520681":87459.0,"521696":61069.0,"523367":139036.0,"524604":116031.0,"531050":123740.0,"535862":50048.0,"558179":174445.0,"558342":28022.0,"559362":32694.0,"560299":52236.0,"563060":27004.0,"565564":9128.0,"565763":66856.0,"566605":47116.0,"584635":81163.0,"585955":32403.0,"600799":20982.0,"605868":58045.0,"606079":117636.0,"616782":13443.0,"632106":34161.0,"643690":26897.0,"651165":19175.0,"663463":22832.0,"675973":29055.0,"686139":31531.0,"718833":77539.0,"736214":22086.0,"786454":19424.0,"852203":80101.0,"862140":69773.0,"867986":77549.0,"871970":61821.0,"876199":63627.0,"879512":17498.0,"884431":59226.0,"890432":8830.0,"899376":59774.0,"900465":54866.0,"926528":51968.0,"937852":50442.0,"940682":19027.0,"1081830":1134.0,"1107961":15345.0,"1122969":56459.0,"1212437":907.0,"1255697":5810.0,"1345835":639.0,"1411669":1521.0,"1483303":3939.0,"1513835":510.0},"price":{"413414":497.0,"417897":157.0,"420012":146.0,"421564":289.0,"424304":91.0,"424624":69.0,"428207":219.0,"433706":29.0,"434476":895.0,"437977":355.0,"441712":732.0,"445018":176.0,"445944":36.0,"447729":47.0,"450769":73.0,"452756":201.0,"452938":69.0,"454861":61.0,"457762":105.0,"459771":123.0,"462000":205.0,"467443":80.0,"469692":89.0,"472132":292.0,"476122":221.0,"481752":119.0,"483568":327.0,"484202":159.0,"485550":143.0,"485707":85.0,"486613":463.0,"487631":87.0,"491823":43.0,"494104":221.0,"495511":121.0,"496353":279.0,"510009":253.0,"510032":152.0,"511502":20.0,"512239":136.0,"518498":259.0,"519869":57.0,"520681":48.0,"521696":68.0,"523367":29.0,"524604":35.0,"531050":32.0,"535862":79.0,"558179":20.0,"558342":129.0,"559362":110.0,"560299":68.0,"563060":132.0,"565564":386.0,"565763":52.0,"566605":74.0,"584635":40.0,"585955":100.0,"600799":147.0,"605868":52.0,"606079":25.0,"616782":217.0,"632106":80.0,"643690":98.0,"651165":134.0,"663463":108.0,"675973":81.0,"686139":72.0,"718833":26.0,"736214":87.0,"786454":84.0,"852203":16.0,"862140":18.0,"867986":16.0,"871970":20.0,"876199":19.0,"879512":70.0,"884431":20.0,"890432":135.0,"899376":19.0,"900465":21.0,"926528":20.0,"937852":20.0,"940682":54.0,"1081830":617.0,"1107961":42.0,"1122969":11.0,"1212437":551.0,"1255697":77.0,"1345835":567.0,"1411669":204.0,"1483303":67.0,"1513835":485.0},"date":{"413414":1751241600,"417897":1751241600,"420012":1751241600,"421564":1751241600,"424304":1751241600,"424624":1751241600,"428207":1751241600,"433706":1751241600,"434476":1751241600,"437977":1751241600,"441712":1751241600,"445018":1751241600,"445944":1751241600,"447729":1751241600,"450769":1751241600,"452756":1751241600,"452938":1751241600,"454861":1751241600,"457762":1751241600,"459771":1751241600,"462000":1751241600,"467443":1751241600,"469692":1751241600,"472132":1751241600,"476122":1751241600,"481752":1751241600,"483568":1751241600,"484202":1751241600,"485550":1751241600,"485707":1751241600,"486613":1751241600,"487631":1751241600,"491823":1751241600,"494104":1751241600,"495511":1751241600,"496353":1751241600,"510009":1751241600,"510032":1751241600,"511502":1751241600,"512239":1751241600,"518498":1751241600,"519869":1751241600,"520681":1751241600,"521696":1751241600,"523367":1751241600,"524604":1751241600,"531050":1751241600,"535862":1751241600,"558179":1751241600,"558342":1751241600,"559362":1751241600,"560299":1751241600,"563060":1751241600,"565564":1751241600,"565763":1751241600,"566605":1751241600,"584635":1751241600,"585955":1751241600,"600799":1751241600,"605868":1751241600,"606079":1751241600,"616782":1751241600,"632106":1751241600,"643690":1751241600,"651165":1751241600,"663463":1751241600,"675973":1751241600,"686139":1751241600,"718833":1751241600,"736214":1751241600,"786454":1751241600,"852203":1751241600,"862140":1751241600,"867986":1751241600,"871970":1751241600,"876199":1751241600,"879512":1751241600,"884431":1751241600,"890432":1751241600,"899376":1751241600,"900465":1751241600,"926528":1751241600,"937852":1751241600,"940682":1751241600,"1081830":1751241600,"1107961":1751241600,"1122969":1751241600,"1212437":1751241600,"1255697":1751241600,"1345835":1751241600,"1411669":1751241600,"1483303":1751241600,"1513835":1751241600},"pct":{"413414":0.0197,"417897":0.0193,"420012":0.0191,"421564":0.019,"424304":0.0188,"424624":0.0187,"428207":0.0185,"433706":0.018,"434476":0.0179,"437977":0.0177,"441712":0.0174,"445018":0.0171,"445944":0.0171,"447729":0.0169,"450769":0.0167,"452756":0.0166,"452938":0.0166,"454861":0.0164,"457762":0.0162,"459771":0.0161,"462000":0.0159,"467443":0.0156,"469692":0.0154,"472132":0.0153,"476122":0.015,"481752":0.0147,"483568":0.0146,"484202":0.0145,"485550":0.0144,"485707":0.0144,"486613":0.0144,"487631":0.0143,"491823":0.0141,"494104":0.0139,"495511":0.0139,"496353":0.0138,"510009":0.0131,"510032":0.0131,"511502":0.013,"512239":0.013,"518498":0.0126,"519869":0.0126,"520681":0.0125,"521696":0.0125,"523367":0.0124,"524604":0.0123,"531050":0.012,"535862":0.0118,"558179":0.0108,"558342":0.0108,"559362":0.0108,"560299":0.0107,"563060":0.0106,"565564":0.0105,"565763":0.0105,"566605":0.0105,"584635":0.0098,"585955":0.0097,"600799":0.0092,"605868":0.009,"606079":0.009,"616782":0.0087,"632106":0.0082,"643690":0.0079,"651165":0.0077,"663463":0.0074,"675973":0.0071,"686139":0.0068,"718833":0.0061,"736214":0.0058,"786454":0.0049,"852203":0.004,"862140":0.0039,"867986":0.0038,"871970":0.0038,"876199":0.0037,"879512":0.0037,"884431":0.0036,"890432":0.0036,"899376":0.0035,"900465":0.0035,"926528":0.0032,"937852":0.0031,"940682":0.0031,"1081830":0.0021,"1107961":0.0019,"1122969":0.0019,"1212437":0.0015,"1255697":0.0013,"1345835":0.0011,"1411669":0.0009,"1483303":0.0008,"1513835":0.0007},"chg":{"413414":-0.0042,"417897":null,"420012":-0.0327,"421564":-0.044,"424304":-0.0143,"424624":-0.0104,"428207":0.017,"433706":-0.0434,"434476":0.0165,"437977":-0.0341,"441712":-0.08,"445018":0.0264,"445944":-0.0632,"447729":null,"450769":-0.1026,"452756":-0.0134,"452938":null,"454861":-0.013,"457762":-0.1255,"459771":0.0191,"462000":0.0156,"467443":0.0111,"469692":-0.0054,"472132":0.0317,"476122":-0.0011,"481752":0.0546,"483568":0.0062,"484202":0.0647,"485550":0.0814,"485707":0.0151,"486613":0.0157,"487631":0.0394,"491823":0.0313,"494104":0.0472,"495511":0.0548,"496353":0.0201,"510009":0.0475,"510032":0.0278,"511502":0.0072,"512239":-0.0047,"518498":0.002,"519869":0.0617,"520681":0.0207,"521696":0.0474,"523367":0.0592,"524604":-0.0043,"531050":0.0554,"535862":0.132,"558179":0.0386,"558342":0.0095,"559362":0.0708,"560299":0.01,"563060":0.0687,"565564":-0.1394,"565763":0.062,"566605":0.0525,"584635":0.0228,"585955":-0.0347,"600799":0.0202,"605868":0.0313,"606079":-0.0126,"616782":0.0568,"632106":0.0374,"643690":-0.0261,"651165":0.0985,"663463":0.023,"675973":0.0227,"686139":0.0357,"718833":-0.1057,"736214":0.0532,"786454":0.0627,"852203":0.0338,"862140":0.0343,"867986":0.0419,"871970":0.0347,"876199":0.0304,"879512":-0.1373,"884431":0.0429,"890432":0.0402,"899376":0.0327,"900465":0.0492,"926528":0.0895,"937852":-0.0174,"940682":0.0462,"1081830":-0.0224,"1107961":0.0541,"1122969":-0.1513,"1212437":-0.0848,"1255697":0.0,"1345835":-0.0154,"1411669":-0.0162,"1483303":-0.1186,"1513835":-0.0097}}