{"ticker":{"8994":"CG","9573":"CG","12683":"CG","12586":"CG","12544":"CG"},"date":{"8994":"2025-08-12 00:00:00.000000","9573":"2025-08-11 00:00:00.000000","12683":"2025-08-01 00:00:00.000000","12586":"2025-08-01 00:00:00.000000","12544":"2025-08-01 00:00:00.000000"},"transactionvalue":{"8994":13013878.0,"9573":6074464.0,"12683":809447.0,"12586":2671345.0,"12544":5527703.0},"transactionshares":{"8994":-202606,"9573":-97394,"12683":-13344,"12586":-44038,"12544":-91126},"securitytitle":{"8994":"Common Stock","9573":"Common Stock","12683":"Common Stock","12586":"Common Stock","12544":"Common Stock"},"transactioncode":{"8994":"S","9573":"S","12683":"F","12586":"F","12544":"F"},"securityadcode":{"8994":"ND","9573":"ND","12683":"ND","12586":"ND","12544":"ND"},"issuername":{"8994":"CARLYLE GROUP INC","9573":"CARLYLE GROUP INC","12683":"CARLYLE GROUP INC","12586":"CARLYLE GROUP INC","12544":"CARLYLE GROUP INC"},"ownername":{"8994":"FERGUSON JEFFREY W","9573":"FERGUSON JEFFREY W","12683":"ANDREWS CHARLES ELLIOTT JR","12586":"FERGUSON JEFFREY W","12544":"REDETT JOHN C"},"officertitle":{"8994":"General Counsel","9573":"General Counsel","12683":"Chief Accounting Officer","12586":"General Counsel","12544":"Chief Financial Officer"},"isofficer":{"8994":"Y","9573":"Y","12683":"Y","12586":"Y","12544":"Y"},"isdirector":{"8994":"N","9573":"N","12683":"N","12586":"N","12544":"N"},"istenpercentowner":{"8994":"N","9573":"N","12683":"N","12586":"N","12544":"N"},"transactionpricepershare":{"8994":64.15,"9573":62.37,"12683":60.66,"12586":60.66,"12544":60.66}}