{"ticker":{"3275":"DUOL","3190":"DUOL","3460":"DUOL","3461":"DUOL","5822":"DUOL","5949":"DUOL","5950":"DUOL","6367":"DUOL","7274":"DUOL","7161":"DUOL","7261":"DUOL","7149":"DUOL","11556":"DUOL","11660":"DUOL","11661":"DUOL","15956":"DUOL","16036":"DUOL","16037":"DUOL","18882":"DUOL","18947":"DUOL","18948":"DUOL","20026":"DUOL","24186":"DUOL","24318":"DUOL","24319":"DUOL","26678":"DUOL"},"date":{"3275":"2025-08-26 00:00:00.000000","3190":"2025-08-26 00:00:00.000000","3460":"2025-08-26 00:00:00.000000","3461":"2025-08-26 00:00:00.000000","5822":"2025-08-19 00:00:00.000000","5949":"2025-08-19 00:00:00.000000","5950":"2025-08-19 00:00:00.000000","6367":"2025-08-18 00:00:00.000000","7274":"2025-08-15 00:00:00.000000","7161":"2025-08-15 00:00:00.000000","7261":"2025-08-15 00:00:00.000000","7149":"2025-08-15 00:00:00.000000","11556":"2025-08-05 00:00:00.000000","11660":"2025-08-05 00:00:00.000000","11661":"2025-08-05 00:00:00.000000","15956":"2025-07-21 00:00:00.000000","16036":"2025-07-21 00:00:00.000000","16037":"2025-07-21 00:00:00.000000","18882":"2025-07-07 00:00:00.000000","18947":"2025-07-07 00:00:00.000000","18948":"2025-07-07 00:00:00.000000","20026":"2025-07-01 00:00:00.000000","24186":"2025-06-20 00:00:00.000000","24318":"2025-06-20 00:00:00.000000","24319":"2025-06-20 00:00:00.000000","26678":"2025-06-13 00:00:00.000000"},"transactionvalue":{"3275":486860.0,"3190":3471322.0,"3460":19871.0,"3461":19871.0,"5822":3445585.0,"5949":380800.0,"5950":380800.0,"6367":907091.0,"7274":421816.0,"7161":833433.0,"7261":475119.0,"7149":920297.0,"11556":3444077.0,"11660":380800.0,"11661":380800.0,"15956":3603335.0,"16036":380800.0,"16037":380800.0,"18882":3928884.0,"18947":380800.0,"18948":380800.0,"20026":1090582.0,"24186":4711990.0,"24318":380800.0,"24319":380800.0,"26678":426777.0},"transactionshares":{"3275":-1515,"3190":-10937,"3460":1378,"3461":-1378,"5822":-10000,"5949":10000,"5950":-10000,"6367":-2471,"7274":-1282,"7161":-2533,"7261":-1444,"7149":-2797,"11556":-10000,"11660":10000,"11661":-10000,"15956":-10000,"16036":10000,"16037":-10000,"18882":-10000,"18947":10000,"18948":-10000,"20026":-2709,"24186":-10000,"24318":10000,"24319":-10000,"26678":-895},"securitytitle":{"3275":"Class A Common Stock","3190":"Class A Common Stock","3460":"Class A Common Stock","3461":"Stock Option Right to Buy","5822":"Class A Common Stock","5949":"Class A Common Stock","5950":"Stock Option Right to Buy","6367":"Class A Common Stock","7274":"Class A Common Stock","7161":"Class A Common Stock","7261":"Class A Common Stock","7149":"Class A Common Stock","11556":"Class A Common Stock","11660":"Class A Common Stock","11661":"Stock Option Right to Buy","15956":"Class A Common Stock","16036":"Class A Common Stock","16037":"Stock Option Right to Buy","18882":"Class A Common Stock","18947":"Class A Common Stock","18948":"Stock Option Right to Buy","20026":"Class A Common Stock","24186":"Class A Common Stock","24318":"Class A Common Stock","24319":"Stock Option Right to Buy","26678":"Class A Common Stock"},"transactioncode":{"3275":"S","3190":"S","3460":"M","3461":"M","5822":"S","5949":"C","5950":"M","6367":"S","7274":"S","7161":"S","7261":"S","7149":"S","11556":"S","11660":"C","11661":"M","15956":"S","16036":"C","16037":"M","18882":"S","18947":"C","18948":"M","20026":"S","24186":"S","24318":"C","24319":"M","26678":"S"},"securityadcode":{"3275":"ND","3190":"ND","3460":null,"3461":"DD","5822":"ND","5949":null,"5950":"DD","6367":"ND","7274":"ND","7161":"ND","7261":"ND","7149":"ND","11556":"ND","11660":null,"11661":"DD","15956":"ND","16036":null,"16037":"DD","18882":"ND","18947":null,"18948":"DD","20026":"ND","24186":"ND","24318":null,"24319":"DD","26678":"ND"},"issuername":{"3275":"DUOLINGO INC","3190":"DUOLINGO INC","3460":"DUOLINGO INC","3461":"DUOLINGO INC","5822":"DUOLINGO INC","5949":"DUOLINGO INC","5950":"DUOLINGO INC","6367":"DUOLINGO INC","7274":"DUOLINGO INC","7161":"DUOLINGO INC","7261":"DUOLINGO INC","7149":"DUOLINGO INC","11556":"DUOLINGO INC","11660":"DUOLINGO INC","11661":"DUOLINGO INC","15956":"DUOLINGO INC","16036":"DUOLINGO INC","16037":"DUOLINGO INC","18882":"DUOLINGO INC","18947":"DUOLINGO INC","18948":"DUOLINGO INC","20026":"DUOLINGO INC","24186":"DUOLINGO INC","24318":"DUOLINGO INC","24319":"DUOLINGO INC","26678":"DUOLINGO INC"},"ownername":{"3275":"CHEN STEPHEN C","3190":"SKARUPPA MATTHEW","3460":"SKARUPPA MATTHEW","3461":"SKARUPPA MATTHEW","5822":"HACKER SEVERIN","5949":"HACKER SEVERIN","5950":"HACKER SEVERIN","6367":"GLANCE NATALIE","7274":"CHEN STEPHEN C","7161":"GLANCE NATALIE","7261":"MEESE ROBERT","7149":"SKARUPPA MATTHEW","11556":"HACKER SEVERIN","11660":"HACKER SEVERIN","11661":"HACKER SEVERIN","15956":"HACKER SEVERIN","16036":"HACKER SEVERIN","16037":"HACKER SEVERIN","18882":"HACKER SEVERIN","18947":"HACKER SEVERIN","18948":"HACKER SEVERIN","20026":"GLANCE NATALIE","24186":"HACKER SEVERIN","24318":"HACKER SEVERIN","24319":"HACKER SEVERIN","26678":"SHELTON JAMES H"},"officertitle":{"3275":"General Counsel","3190":"Chief Financial Officer","3460":"Chief Financial Officer","3461":"Chief Financial Officer","5822":"Chief Tech Officer Co-Founder","5949":"Chief Tech Officer Co-Founder","5950":"Chief Tech Officer Co-Founder","6367":"Chief Engineering Officer","7274":"General Counsel","7161":"Chief Engineering Officer","7261":"Chief Business Officer","7149":"Chief Financial Officer","11556":"Chief Tech Officer Co-Founder","11660":"Chief Tech Officer Co-Founder","11661":"Chief Tech Officer Co-Founder","15956":"Chief Tech Officer Co-Founder","16036":"Chief Tech Officer Co-Founder","16037":"Chief Tech Officer Co-Founder","18882":"Chief Tech Officer Co-Founder","18947":"Chief Tech Officer Co-Founder","18948":"Chief Tech Officer Co-Founder","20026":"Chief Engineering Officer","24186":"Chief Tech Officer Co-Founder","24318":"Chief Tech Officer Co-Founder","24319":"Chief Tech Officer Co-Founder","26678":null},"isofficer":{"3275":"Y","3190":"Y","3460":"Y","3461":"Y","5822":"Y","5949":"Y","5950":"Y","6367":"Y","7274":"Y","7161":"Y","7261":"Y","7149":"Y","11556":"Y","11660":"Y","11661":"Y","15956":"Y","16036":"Y","16037":"Y","18882":"Y","18947":"Y","18948":"Y","20026":"Y","24186":"Y","24318":"Y","24319":"Y","26678":"N"},"isdirector":{"3275":"N","3190":"N","3460":"N","3461":"N","5822":"Y","5949":"Y","5950":"Y","6367":"N","7274":"N","7161":"N","7261":"N","7149":"N","11556":"Y","11660":"Y","11661":"Y","15956":"Y","16036":"Y","16037":"Y","18882":"Y","18947":"Y","18948":"Y","20026":"N","24186":"Y","24318":"Y","24319":"Y","26678":"Y"},"istenpercentowner":{"3275":"N","3190":"N","3460":"N","3461":"N","5822":"Y","5949":"Y","5950":"Y","6367":"N","7274":"N","7161":"N","7261":"N","7149":"N","11556":"Y","11660":"Y","11661":"Y","15956":"Y","16036":"Y","16037":"Y","18882":"Y","18947":"Y","18948":"Y","20026":"N","24186":"Y","24318":"Y","24319":"Y","26678":"N"},"transactionpricepershare":{"3275":321.36,"3190":316.67,"3460":14.42,"3461":14.42,"5822":349.14,"5949":38.08,"5950":38.08,"6367":367.31,"7274":329.03,"7161":329.03,"7261":329.03,"7149":329.03,"11556":346.79,"11660":38.08,"11661":38.08,"15956":362.07,"16036":38.08,"16037":38.08,"18882":392.48,"18947":38.08,"18948":38.08,"20026":403.71,"24186":472.52,"24318":38.08,"24319":38.08,"26678":476.85}}