{"ticker":{"1703":"FELE","1741":"FELE","8573":"FELE","8574":"FELE","13095":"FELE","13190":"FELE","20698":"FELE","20929":"FELE"},"date":{"1703":"2025-09-01 00:00:00.000000","1741":"2025-09-01 00:00:00.000000","8573":"2025-08-13 00:00:00.000000","8574":"2025-08-13 00:00:00.000000","13095":"2025-08-01 00:00:00.000000","13190":"2025-08-01 00:00:00.000000","20698":"2025-07-01 00:00:00.000000","20929":"2025-07-01 00:00:00.000000"},"transactionvalue":{"1703":35817.0,"1741":14190.0,"8573":983869.0,"8574":981940.0,"13095":34093.0,"13190":13507.0,"20698":33590.0,"20929":13307.0},"transactionshares":{"1703":366,"1741":-145,"8573":-10036,"8574":-10000,"13095":366,"13190":-145,"20698":366,"20929":-145},"securitytitle":{"1703":"common stock","1741":"common stock","8573":"common stock","8574":"common stock","13095":"common stock","13190":"common stock","20698":"common stock","20929":"common stock"},"transactioncode":{"1703":"A","1741":"F","8573":"S","8574":"S","13095":"A","13190":"F","20698":"A","20929":"F"},"securityadcode":{"1703":null,"1741":"ND","8573":"ND","8574":"ND","13095":null,"13190":"ND","20698":null,"20929":"ND"},"issuername":{"1703":"FRANKLIN ELECTRIC CO INC","1741":"FRANKLIN ELECTRIC CO INC","8573":"FRANKLIN ELECTRIC CO INC","8574":"FRANKLIN ELECTRIC CO INC","13095":"FRANKLIN ELECTRIC CO INC","13190":"FRANKLIN ELECTRIC CO INC","20698":"FRANKLIN ELECTRIC CO INC","20929":"FRANKLIN ELECTRIC CO INC"},"ownername":{"1703":"SENGSTACK GREGG C","1741":"SENGSTACK GREGG C","8573":"GRANDON JONATHAN M","8574":"SENGSTACK GREGG C","13095":"SENGSTACK GREGG C","13190":"SENGSTACK GREGG C","20698":"SENGSTACK GREGG C","20929":"SENGSTACK GREGG C"},"officertitle":{"1703":null,"1741":null,"8573":"Chief Administrative Officer","8574":null,"13095":null,"13190":null,"20698":null,"20929":null},"isofficer":{"1703":"N","1741":"N","8573":"Y","8574":"N","13095":"N","13190":"N","20698":"N","20929":"N"},"isdirector":{"1703":"Y","1741":"Y","8573":"N","8574":"Y","13095":"Y","13190":"Y","20698":"Y","20929":"Y"},"istenpercentowner":{"1703":"N","1741":"N","8573":"N","8574":"N","13095":"N","13190":"N","20698":"N","20929":"N"},"transactionpricepershare":{"1703":97.86,"1741":97.86,"8573":98.03,"8574":98.19,"13095":93.15,"13190":93.15,"20698":91.78,"20929":91.78}}