{"ticker":{"3007":"KE","2866":"KE","2958":"KE","2933":"KE","2863":"KE","2799":"KE","2920":"KE"},"date":{"3007":"2025-08-27 00:00:00.000000","2866":"2025-08-27 00:00:00.000000","2958":"2025-08-27 00:00:00.000000","2933":"2025-08-27 00:00:00.000000","2863":"2025-08-27 00:00:00.000000","2799":"2025-08-27 00:00:00.000000","2920":"2025-08-27 00:00:00.000000"},"transactionvalue":{"3007":98818.0,"2866":383497.0,"2958":156045.0,"2933":191371.0,"2863":388363.0,"2799":1383788.0,"2920":221774.0},"transactionshares":{"3007":-3533,"2866":-13711,"2958":-5579,"2933":-6842,"2863":-13885,"2799":-49474,"2920":-7929},"securitytitle":{"3007":"Common Stock","2866":"Common Stock","2958":"Common Stock","2933":"Common Stock","2863":"Common Stock","2799":"Common Stock","2920":"Common Stock"},"transactioncode":{"3007":"F","2866":"F","2958":"F","2933":"F","2863":"F","2799":"F","2920":"F"},"securityadcode":{"3007":"ND","2866":"ND","2958":"ND","2933":"ND","2863":"ND","2799":"ND","2920":"ND"},"issuername":{"3007":"KIMBALL ELECTRONICS INC","2866":"KIMBALL ELECTRONICS INC","2958":"KIMBALL ELECTRONICS INC","2933":"KIMBALL ELECTRONICS INC","2863":"KIMBALL ELECTRONICS INC","2799":"KIMBALL ELECTRONICS INC","2920":"KIMBALL ELECTRONICS INC"},"ownername":{"3007":"BAUMANN ADAM M","2866":"CROOM JANA T","2958":"DELORENZO JESSICA L","2933":"HASS DOUGLAS","2863":"KORN STEVEN T","2799":"PHILLIPS RICHARD D","2920":"THOMSON KATHY R"},"officertitle":{"3007":"Chief Accounting Officer","2866":"CFO","2958":"Chief Human Resources Officer","2933":"CL  AO Secretary","2863":"Chief Operating Officer","2799":"CEO and Director","2920":"Chief Commercial Officer"},"isofficer":{"3007":"Y","2866":"Y","2958":"Y","2933":"Y","2863":"Y","2799":"Y","2920":"Y"},"isdirector":{"3007":"N","2866":"N","2958":"N","2933":"N","2863":"N","2799":"Y","2920":"N"},"istenpercentowner":{"3007":"N","2866":"N","2958":"N","2933":"N","2863":"N","2799":"N","2920":"N"},"transactionpricepershare":{"3007":27.97,"2866":27.97,"2958":27.97,"2933":27.97,"2863":27.97,"2799":27.97,"2920":27.97}}