{"ticker":{"11980":"KMB","13618":"KMB","13485":"KMB","14094":"KMB"},"date":{"11980":"2025-08-04 00:00:00.000000","13618":"2025-07-31 00:00:00.000000","13485":"2025-07-31 00:00:00.000000","14094":"2025-07-29 00:00:00.000000"},"transactionvalue":{"11980":2006114.0,"13618":47979.0,"13485":266812.0,"14094":2756636.0},"transactionshares":{"11980":-15038,"13618":-385,"13485":-2141,"14094":-21548},"securitytitle":{"11980":"Common Stock","13618":"Common Stock","13485":"Common Stock","14094":"Common Stock"},"transactioncode":{"11980":"S","13618":"F","13485":"F","14094":"F"},"securityadcode":{"11980":"ND","13618":"ND","13485":"ND","14094":"ND"},"issuername":{"11980":"KIMBERLY CLARK CORP","13618":"KIMBERLY CLARK CORP","13485":"KIMBERLY CLARK CORP","14094":"KIMBERLY CLARK CORP"},"ownername":{"11980":"HICKS ZACKERY A","13618":"CORSI PATRICIA","13485":"SLAVTCHEFF CRAIG","14094":"HICKS ZACKERY A"},"officertitle":{"11980":"Chief Digital  Technology Off","13618":"Chief Growth Officer","13485":"Chief RD Officer","14094":"Chief Digital  Technology Off"},"isofficer":{"11980":"Y","13618":"Y","13485":"Y","14094":"Y"},"isdirector":{"11980":"N","13618":"N","13485":"N","14094":"N"},"istenpercentowner":{"11980":"N","13618":"N","13485":"N","14094":"N"},"transactionpricepershare":{"11980":133.4,"13618":124.62,"13485":124.62,"14094":127.93}}