{"ticker":{"27773":"LAZ"},"date":{"27773":"2025-06-11 00:00:00.000000"},"transactionvalue":{"27773":3763016.0},"transactionshares":{"27773":-85894},"securitytitle":{"27773":"Common Stock"},"transactioncode":{"27773":"S"},"securityadcode":{"27773":"ND"},"issuername":{"27773":"LAZARD INC"},"ownername":{"27773":"SOTO ALEXANDRA"},"officertitle":{"27773":"Chief Operating Officer"},"isofficer":{"27773":"Y"},"isdirector":{"27773":"N"},"istenpercentowner":{"27773":"N"},"transactionpricepershare":{"27773":43.81}}