{"index":{"34192":34192,"35532":35532,"38933":38933,"39090":39090,"39118":39118,"39169":39169,"42203":42203,"44578":44578,"45989":45989,"47998":47998,"48279":48279,"48650":48650,"53178":53178,"57785":57785,"59403":59403,"66255":66255,"67054":67054,"70846":70846,"71198":71198,"78494":78494,"80367":80367,"80916":80916,"81191":81191,"81547":81547,"84235":84235,"85248":85248,"88053":88053,"89588":89588,"90052":90052,"94724":94724,"96379":96379,"96955":96955,"98003":98003,"98326":98326,"100390":100390,"103714":103714,"104578":104578,"106224":106224,"108769":108769,"109507":109507,"118239":118239,"121760":121760,"123051":123051,"123229":123229,"126973":126973,"137894":137894,"138220":138220,"142048":142048,"157981":157981,"162940":162940,"172264":172264,"177780":177780,"179765":179765,"185071":185071,"187615":187615,"187926":187926,"207691":207691,"214814":214814,"231616":231616,"253070":253070,"253417":253417,"261781":261781,"263031":263031,"276073":276073,"397214":397214,"502823":502823,"539731":539731,"593753":593753,"758849":758849,"925489":925489,"1017223":1017223,"1094908":1094908,"1127639":1127639,"1227370":1227370,"1273570":1273570,"1280009":1280009,"1299229":1299229,"1317851":1317851,"1317948":1317948,"1354079":1354079,"1403396":1403396,"1427626":1427626,"1434663":1434663,"1519933":1519933,"1562247":1562247,"1583603":1583603,"1663371":1663371,"1669315":1669315,"1698699":1698699,"1704576":1704576,"1709760":1709760,"1751877":1751877},"ticker":{"34192":"TD","35532":"BNS","38933":"RY","39090":"BMO","39118":"RCI","39169":"MFC","42203":"SLF","44578":"NTR","45989":"OTEX","47998":"MGA","48279":"META","48650":"GOOGL","53178":"CM","57785":"BCE","59403":"T","66255":"TU","67054":"B","70846":"CAE","71198":"PFE","78494":"HBM","80367":"C","80916":"CVE","81191":"WFG","81547":"ILMN","84235":"SU","85248":"CVS","88053":"STT","89588":"TFC","90052":"VZ","94724":"INTC","96379":"CMCSA","96955":"ADBE","98003":"GSK","98326":"EMN","100390":"ELP","103714":"GILD","104578":"TECK","106224":"SWKS","108769":"WFC","109507":"ABBV","118239":"SBS","121760":"FDX","123051":"CRUS","123229":"BAC","126973":"SHEL","137894":"EFXT","138220":"WMT","142048":"COP","157981":"GPK","162940":"QSR","172264":"ADNT","177780":"MRK","179765":"MAC","185071":"CX","187615":"MRNA","187926":"IVZ","207691":"BAP","214814":"CPA","231616":"HES","253070":"LULU","253417":"IBN","261781":"CXM","263031":"BIIB","276073":"AMRZ","397214":"PROF","502823":"HDB","539731":"SW","593753":"XBI","758849":"SCHW","925489":"ING","1017223":"FLIN","1094908":"ORCL","1127639":"UPS","1227370":"PBA","1273570":"SPRY","1280009":"SKX","1299229":"FTS","1317851":"EMA","1317948":"NXPI","1354079":"VALE","1403396":"MSFT","1427626":"FCX","1434663":"MGTX","1519933":"ERO","1562247":"MLYS","1583603":"NAMS","1663371":"TCRX","1669315":"AURA","1698699":"ETNB","1704576":"REPL","1709760":"HUMA","1751877":"ALDX"},"investorname":{"34192":"LETKO BROSSEAU ASSOCIATES INC","35532":"LETKO BROSSEAU ASSOCIATES INC","38933":"LETKO BROSSEAU ASSOCIATES INC","39090":"LETKO BROSSEAU ASSOCIATES INC","39118":"LETKO BROSSEAU ASSOCIATES INC","39169":"LETKO BROSSEAU ASSOCIATES INC","42203":"LETKO BROSSEAU ASSOCIATES INC","44578":"LETKO BROSSEAU ASSOCIATES INC","45989":"LETKO BROSSEAU ASSOCIATES INC","47998":"LETKO BROSSEAU ASSOCIATES INC","48279":"LETKO BROSSEAU ASSOCIATES INC","48650":"LETKO BROSSEAU ASSOCIATES INC","53178":"LETKO BROSSEAU ASSOCIATES INC","57785":"LETKO BROSSEAU ASSOCIATES INC","59403":"LETKO BROSSEAU ASSOCIATES INC","66255":"LETKO BROSSEAU ASSOCIATES INC","67054":"LETKO BROSSEAU ASSOCIATES INC","70846":"LETKO BROSSEAU ASSOCIATES INC","71198":"LETKO BROSSEAU ASSOCIATES INC","78494":"LETKO BROSSEAU ASSOCIATES INC","80367":"LETKO BROSSEAU ASSOCIATES INC","80916":"LETKO BROSSEAU ASSOCIATES INC","81191":"LETKO BROSSEAU ASSOCIATES INC","81547":"LETKO BROSSEAU ASSOCIATES INC","84235":"LETKO BROSSEAU ASSOCIATES INC","85248":"LETKO BROSSEAU ASSOCIATES INC","88053":"LETKO BROSSEAU ASSOCIATES INC","89588":"LETKO BROSSEAU ASSOCIATES INC","90052":"LETKO BROSSEAU ASSOCIATES INC","94724":"LETKO BROSSEAU ASSOCIATES INC","96379":"LETKO BROSSEAU ASSOCIATES INC","96955":"LETKO BROSSEAU ASSOCIATES INC","98003":"LETKO BROSSEAU ASSOCIATES INC","98326":"LETKO BROSSEAU ASSOCIATES INC","100390":"LETKO BROSSEAU ASSOCIATES INC","103714":"LETKO BROSSEAU ASSOCIATES INC","104578":"LETKO BROSSEAU ASSOCIATES INC","106224":"LETKO BROSSEAU ASSOCIATES INC","108769":"LETKO BROSSEAU ASSOCIATES INC","109507":"LETKO BROSSEAU ASSOCIATES INC","118239":"LETKO BROSSEAU ASSOCIATES INC","121760":"LETKO BROSSEAU ASSOCIATES INC","123051":"LETKO BROSSEAU ASSOCIATES INC","123229":"LETKO BROSSEAU ASSOCIATES INC","126973":"LETKO BROSSEAU ASSOCIATES INC","137894":"LETKO BROSSEAU ASSOCIATES INC","138220":"LETKO BROSSEAU ASSOCIATES INC","142048":"LETKO BROSSEAU ASSOCIATES INC","157981":"LETKO BROSSEAU ASSOCIATES INC","162940":"LETKO BROSSEAU ASSOCIATES INC","172264":"LETKO BROSSEAU ASSOCIATES INC","177780":"LETKO BROSSEAU ASSOCIATES INC","179765":"LETKO BROSSEAU ASSOCIATES INC","185071":"LETKO BROSSEAU ASSOCIATES INC","187615":"LETKO BROSSEAU ASSOCIATES INC","187926":"LETKO BROSSEAU ASSOCIATES INC","207691":"LETKO BROSSEAU ASSOCIATES INC","214814":"LETKO BROSSEAU ASSOCIATES INC","231616":"LETKO BROSSEAU ASSOCIATES INC","253070":"LETKO BROSSEAU ASSOCIATES INC","253417":"LETKO BROSSEAU ASSOCIATES INC","261781":"LETKO BROSSEAU ASSOCIATES INC","263031":"LETKO BROSSEAU ASSOCIATES INC","276073":"LETKO BROSSEAU ASSOCIATES INC","397214":"LETKO BROSSEAU ASSOCIATES INC","502823":"LETKO BROSSEAU ASSOCIATES INC","539731":"LETKO BROSSEAU ASSOCIATES INC","593753":"LETKO BROSSEAU ASSOCIATES INC","758849":"LETKO BROSSEAU ASSOCIATES INC","925489":"LETKO BROSSEAU ASSOCIATES INC","1017223":"LETKO BROSSEAU ASSOCIATES INC","1094908":"LETKO BROSSEAU ASSOCIATES INC","1127639":"LETKO BROSSEAU ASSOCIATES INC","1227370":"LETKO BROSSEAU ASSOCIATES INC","1273570":"LETKO BROSSEAU ASSOCIATES INC","1280009":"LETKO BROSSEAU ASSOCIATES INC","1299229":"LETKO BROSSEAU ASSOCIATES INC","1317851":"LETKO BROSSEAU ASSOCIATES INC","1317948":"LETKO BROSSEAU ASSOCIATES INC","1354079":"LETKO BROSSEAU ASSOCIATES INC","1403396":"LETKO BROSSEAU ASSOCIATES INC","1427626":"LETKO BROSSEAU ASSOCIATES INC","1434663":"LETKO BROSSEAU ASSOCIATES INC","1519933":"LETKO BROSSEAU ASSOCIATES INC","1562247":"LETKO BROSSEAU ASSOCIATES INC","1583603":"LETKO BROSSEAU ASSOCIATES INC","1663371":"LETKO BROSSEAU ASSOCIATES INC","1669315":"LETKO BROSSEAU ASSOCIATES INC","1698699":"LETKO BROSSEAU ASSOCIATES INC","1704576":"LETKO BROSSEAU ASSOCIATES INC","1709760":"LETKO BROSSEAU ASSOCIATES INC","1751877":"LETKO BROSSEAU ASSOCIATES INC"},"securitytype":{"34192":"SHR","35532":"SHR","38933":"SHR","39090":"SHR","39118":"SHR","39169":"SHR","42203":"SHR","44578":"SHR","45989":"SHR","47998":"SHR","48279":"SHR","48650":"SHR","53178":"SHR","57785":"SHR","59403":"SHR","66255":"SHR","67054":"SHR","70846":"SHR","71198":"SHR","78494":"SHR","80367":"SHR","80916":"SHR","81191":"SHR","81547":"SHR","84235":"SHR","85248":"SHR","88053":"SHR","89588":"SHR","90052":"SHR","94724":"SHR","96379":"SHR","96955":"SHR","98003":"SHR","98326":"SHR","100390":"SHR","103714":"SHR","104578":"SHR","106224":"SHR","108769":"SHR","109507":"SHR","118239":"SHR","121760":"SHR","123051":"SHR","123229":"SHR","126973":"SHR","137894":"SHR","138220":"SHR","142048":"SHR","157981":"SHR","162940":"SHR","172264":"SHR","177780":"SHR","179765":"SHR","185071":"SHR","187615":"SHR","187926":"SHR","207691":"SHR","214814":"SHR","231616":"SHR","253070":"SHR","253417":"SHR","261781":"SHR","263031":"SHR","276073":"SHR","397214":"SHR","502823":"SHR","539731":"SHR","593753":"FND","758849":"SHR","925489":"SHR","1017223":"FND","1094908":"SHR","1127639":"SHR","1227370":"SHR","1273570":"SHR","1280009":"SHR","1299229":"SHR","1317851":"SHR","1317948":"SHR","1354079":"SHR","1403396":"SHR","1427626":"SHR","1434663":"SHR","1519933":"SHR","1562247":"SHR","1583603":"SHR","1663371":"SHR","1669315":"SHR","1698699":"SHR","1704576":"SHR","1709760":"SHR","1751877":"SHR"},"calendardate":{"34192":"2025-06-30","35532":"2025-06-30","38933":"2025-06-30","39090":"2025-06-30","39118":"2025-06-30","39169":"2025-06-30","42203":"2025-06-30","44578":"2025-06-30","45989":"2025-06-30","47998":"2025-06-30","48279":"2025-06-30","48650":"2025-06-30","53178":"2025-06-30","57785":"2025-06-30","59403":"2025-06-30","66255":"2025-06-30","67054":"2025-06-30","70846":"2025-06-30","71198":"2025-06-30","78494":"2025-06-30","80367":"2025-06-30","80916":"2025-06-30","81191":"2025-06-30","81547":"2025-06-30","84235":"2025-06-30","85248":"2025-06-30","88053":"2025-06-30","89588":"2025-06-30","90052":"2025-06-30","94724":"2025-06-30","96379":"2025-06-30","96955":"2025-06-30","98003":"2025-06-30","98326":"2025-06-30","100390":"2025-06-30","103714":"2025-06-30","104578":"2025-06-30","106224":"2025-06-30","108769":"2025-06-30","109507":"2025-06-30","118239":"2025-06-30","121760":"2025-06-30","123051":"2025-06-30","123229":"2025-06-30","126973":"2025-06-30","137894":"2025-06-30","138220":"2025-06-30","142048":"2025-06-30","157981":"2025-06-30","162940":"2025-06-30","172264":"2025-06-30","177780":"2025-06-30","179765":"2025-06-30","185071":"2025-06-30","187615":"2025-06-30","187926":"2025-06-30","207691":"2025-06-30","214814":"2025-06-30","231616":"2025-06-30","253070":"2025-06-30","253417":"2025-06-30","261781":"2025-06-30","263031":"2025-06-30","276073":"2025-06-30","397214":"2025-06-30","502823":"2025-06-30","539731":"2025-06-30","593753":"2025-06-30","758849":"2025-06-30","925489":"2025-06-30","1017223":"2025-06-30","1094908":"2025-06-30","1127639":"2025-06-30","1227370":"2025-06-30","1273570":"2025-06-30","1280009":"2025-06-30","1299229":"2025-06-30","1317851":"2025-06-30","1317948":"2025-06-30","1354079":"2025-06-30","1403396":"2025-06-30","1427626":"2025-06-30","1434663":"2025-06-30","1519933":"2025-06-30","1562247":"2025-06-30","1583603":"2025-06-30","1663371":"2025-06-30","1669315":"2025-06-30","1698699":"2025-06-30","1704576":"2025-06-30","1709760":"2025-06-30","1751877":"2025-06-30"},"value":{"34192":233766467.0,"35532":223615063.0,"38933":201045201.0,"39090":200103563.0,"39118":199921975.0,"39169":199567385.0,"42203":182534426.0,"44578":171131146.0,"45989":164753579.0,"47998":156297371.0,"48279":155184167.0,"48650":153783826.0,"53178":138391476.0,"57785":125003743.0,"59403":120712358.0,"66255":105710669.0,"67054":104217156.0,"70846":97216168.0,"71198":96617925.0,"78494":85384017.0,"80367":82947482.0,"80916":82258914.0,"81191":81882565.0,"81547":81438923.0,"84235":77953411.0,"85248":76711623.0,"88053":73487427.0,"89588":71899958.0,"90052":71423323.0,"94724":66786608.0,"96379":65226366.0,"96955":64707616.0,"98003":63792691.0,"98326":63505497.0,"100390":61791855.0,"103714":59151362.0,"104578":58524861.0,"106224":57351784.0,"108769":55615618.0,"109507":55126170.0,"118239":49511350.0,"121760":47503698.0,"123051":46816125.0,"123229":46717238.0,"126973":44770339.0,"137894":39832205.0,"138220":39710511.0,"142048":38200972.0,"157981":32716653.0,"162940":31307140.0,"172264":28839000.0,"177780":27491397.0,"179765":27025373.0,"185071":25850979.0,"187615":25332862.0,"187926":25270447.0,"207691":21669370.0,"214814":20542726.0,"231616":18206510.0,"253070":15747753.0,"253417":15713311.0,"261781":14893830.0,"263031":14776291.0,"276073":13631631.0,"397214":7147105.0,"502823":4521997.0,"539731":3902918.0,"593753":3178292.0,"758849":1801625.0,"925489":1081668.0,"1017223":835434.0,"1094908":676660.0,"1127639":620781.0,"1227370":482447.0,"1273570":431015.0,"1280009":424348.0,"1299229":405035.0,"1317851":387903.0,"1317948":387820.0,"1354079":355872.0,"1403396":317348.0,"1427626":300199.0,"1434663":295356.0,"1519933":244412.0,"1562247":223245.0,"1583603":213245.0,"1663371":139019.0,"1669315":132712.0,"1698699":105074.0,"1704576":100332.0,"1709760":96036.0,"1751877":66259.0},"units":{"34192":3184648.0,"35532":4052095.0,"38933":1528535.0,"39090":1809299.0,"39118":6753987.0,"39169":6254242.0,"42203":2748794.0,"44578":2942763.0,"45989":5649818.0,"47998":4051430.0,"48279":210251.0,"48650":866925.0,"53178":1953602.0,"57785":5647934.0,"59403":4171125.0,"66255":6595437.0,"67054":5016025.0,"70846":3323765.0,"71198":3985888.0,"78494":8062733.0,"80367":974477.0,"80916":6057328.0,"81191":1118854.0,"81547":853568.0,"84235":2085227.0,"85248":1112085.0,"88053":691061.0,"89588":1672481.0,"90052":1650643.0,"94724":2981545.0,"96379":1827581.0,"96955":167255.0,"98003":1661268.0,"98326":850596.0,"100390":6772552.0,"103714":533520.0,"104578":1450103.0,"106224":769616.0,"108769":694154.0,"109507":296984.0,"118239":2253589.0,"121760":208982.0,"123051":449054.0,"123229":987262.0,"126973":635852.0,"137894":5055911.0,"138220":406121.0,"142048":425685.0,"157981":1552760.0,"162940":472917.0,"172264":1481963.0,"177780":347289.0,"179765":1670295.0,"185071":3730300.0,"187615":918190.0,"187926":1602438.0,"207691":96946.0,"214814":186803.0,"231616":131417.0,"253070":66284.0,"253417":467102.0,"261781":1760500.0,"263031":117655.0,"276073":274148.0,"397214":1204250.0,"502823":58980.0,"539731":90450.0,"593753":38325.0,"758849":19746.0,"925489":49459.0,"1017223":20975.0,"1094908":3095.0,"1127639":6150.0,"1227370":12875.0,"1273570":24700.0,"1280009":6725.0,"1299229":8500.0,"1317851":8485.0,"1317948":1775.0,"1354079":36650.0,"1403396":638.0,"1427626":6925.0,"1434663":45300.0,"1519933":14500.0,"1562247":16500.0,"1583603":11775.0,"1663371":95875.0,"1669315":21200.0,"1698699":10700.0,"1704576":10800.0,"1709760":45950.0,"1751877":17300.0},"price":{"34192":73.0,"35532":55.0,"38933":131.0,"39090":110.0,"39118":29.0,"39169":31.0,"42203":66.0,"44578":58.0,"45989":29.0,"47998":38.0,"48279":738.0,"48650":177.0,"53178":70.0,"57785":22.0,"59403":28.0,"66255":16.0,"67054":20.0,"70846":29.0,"71198":24.0,"78494":10.0,"80367":85.0,"80916":13.0,"81191":73.0,"81547":95.0,"84235":37.0,"85248":68.0,"88053":106.0,"89588":42.0,"90052":43.0,"94724":22.0,"96379":35.0,"96955":386.0,"98003":38.0,"98326":74.0,"100390":9.0,"103714":110.0,"104578":40.0,"106224":74.0,"108769":80.0,"109507":185.0,"118239":21.0,"121760":227.0,"123051":104.0,"123229":47.0,"126973":70.0,"137894":7.0,"138220":97.0,"142048":89.0,"157981":21.0,"162940":66.0,"172264":19.0,"177780":79.0,"179765":16.0,"185071":6.0,"187615":27.0,"187926":15.0,"207691":223.0,"214814":109.0,"231616":138.0,"253070":237.0,"253417":33.0,"261781":8.0,"263031":125.0,"276073":49.0,"397214":5.0,"502823":76.0,"539731":43.0,"593753":82.0,"758849":91.0,"925489":21.0,"1017223":39.0,"1094908":218.0,"1127639":100.0,"1227370":37.0,"1273570":17.0,"1280009":63.0,"1299229":47.0,"1317851":45.0,"1317948":218.0,"1354079":9.0,"1403396":497.0,"1427626":43.0,"1434663":6.0,"1519933":16.0,"1562247":13.0,"1583603":18.0,"1663371":1.0,"1669315":6.0,"1698699":9.0,"1704576":9.0,"1709760":2.0,"1751877":3.0},"date":{"34192":1751241600,"35532":1751241600,"38933":1751241600,"39090":1751241600,"39118":1751241600,"39169":1751241600,"42203":1751241600,"44578":1751241600,"45989":1751241600,"47998":1751241600,"48279":1751241600,"48650":1751241600,"53178":1751241600,"57785":1751241600,"59403":1751241600,"66255":1751241600,"67054":1751241600,"70846":1751241600,"71198":1751241600,"78494":1751241600,"80367":1751241600,"80916":1751241600,"81191":1751241600,"81547":1751241600,"84235":1751241600,"85248":1751241600,"88053":1751241600,"89588":1751241600,"90052":1751241600,"94724":1751241600,"96379":1751241600,"96955":1751241600,"98003":1751241600,"98326":1751241600,"100390":1751241600,"103714":1751241600,"104578":1751241600,"106224":1751241600,"108769":1751241600,"109507":1751241600,"118239":1751241600,"121760":1751241600,"123051":1751241600,"123229":1751241600,"126973":1751241600,"137894":1751241600,"138220":1751241600,"142048":1751241600,"157981":1751241600,"162940":1751241600,"172264":1751241600,"177780":1751241600,"179765":1751241600,"185071":1751241600,"187615":1751241600,"187926":1751241600,"207691":1751241600,"214814":1751241600,"231616":1751241600,"253070":1751241600,"253417":1751241600,"261781":1751241600,"263031":1751241600,"276073":1751241600,"397214":1751241600,"502823":1751241600,"539731":1751241600,"593753":1751241600,"758849":1751241600,"925489":1751241600,"1017223":1751241600,"1094908":1751241600,"1127639":1751241600,"1227370":1751241600,"1273570":1751241600,"1280009":1751241600,"1299229":1751241600,"1317851":1751241600,"1317948":1751241600,"1354079":1751241600,"1403396":1751241600,"1427626":1751241600,"1434663":1751241600,"1519933":1751241600,"1562247":1751241600,"1583603":1751241600,"1663371":1751241600,"1669315":1751241600,"1698699":1751241600,"1704576":1751241600,"1709760":1751241600,"1751877":1751241600},"pct":{"34192":0.0447,"35532":0.0428,"38933":0.0385,"39090":0.0383,"39118":0.0382,"39169":0.0382,"42203":0.0349,"44578":0.0327,"45989":0.0315,"47998":0.0299,"48279":0.0297,"48650":0.0294,"53178":0.0265,"57785":0.0239,"59403":0.0231,"66255":0.0202,"67054":0.0199,"70846":0.0186,"71198":0.0185,"78494":0.0163,"80367":0.0159,"80916":0.0157,"81191":0.0157,"81547":0.0156,"84235":0.0149,"85248":0.0147,"88053":0.0141,"89588":0.0138,"90052":0.0137,"94724":0.0128,"96379":0.0125,"96955":0.0124,"98003":0.0122,"98326":0.0121,"100390":0.0118,"103714":0.0113,"104578":0.0112,"106224":0.011,"108769":0.0106,"109507":0.0105,"118239":0.0095,"121760":0.0091,"123051":0.009,"123229":0.0089,"126973":0.0086,"137894":0.0076,"138220":0.0076,"142048":0.0073,"157981":0.0063,"162940":0.006,"172264":0.0055,"177780":0.0053,"179765":0.0052,"185071":0.0049,"187615":0.0048,"187926":0.0048,"207691":0.0041,"214814":0.0039,"231616":0.0035,"253070":0.003,"253417":0.003,"261781":0.0028,"263031":0.0028,"276073":0.0026,"397214":0.0014,"502823":0.0009,"539731":0.0007,"593753":0.0006,"758849":0.0003,"925489":0.0002,"1017223":0.0002,"1094908":0.0001,"1127639":0.0001,"1227370":0.0001,"1273570":0.0001,"1280009":0.0001,"1299229":0.0001,"1317851":0.0001,"1317948":0.0001,"1354079":0.0001,"1403396":0.0001,"1427626":0.0001,"1434663":0.0001,"1519933":0.0,"1562247":0.0,"1583603":0.0,"1663371":0.0,"1669315":0.0,"1698699":0.0,"1704576":0.0,"1709760":0.0,"1751877":0.0},"chg":{"34192":-0.0236,"35532":0.0101,"38933":-0.0114,"39090":-0.0095,"39118":0.1476,"39169":-0.0033,"42203":-0.0076,"44578":-0.0196,"45989":0.1623,"47998":0.0233,"48279":-0.007,"48650":0.1401,"53178":-0.0125,"57785":0.0857,"59403":-0.0128,"66255":0.0215,"67054":0.0036,"70846":-0.0181,"71198":0.0359,"78494":-0.0394,"80367":-0.0335,"80916":0.0602,"81191":0.0238,"81547":0.0112,"84235":-0.0013,"85248":-0.0001,"88053":-0.0006,"89588":0.0154,"90052":-0.0003,"94724":0.0266,"96379":0.0062,"96955":0.0444,"98003":0.0258,"98326":0.0254,"100390":-0.0018,"103714":-0.0276,"104578":-0.0079,"106224":0.0527,"108769":-0.0368,"109507":-0.0089,"118239":-0.042,"121760":0.0701,"123051":0.0024,"123229":-0.0012,"126973":-0.0167,"137894":0.0012,"138220":-0.0627,"142048":0.0152,"157981":0.3763,"162940":0.0465,"172264":null,"177780":0.4416,"179765":0.0072,"185071":0.0043,"187615":0.0243,"187926":0.006,"207691":0.0052,"214814":0.0071,"231616":-0.0095,"253070":0.0366,"253417":-0.0225,"261781":0.0066,"263031":0.0177,"276073":null,"397214":-0.003,"502823":0.0288,"539731":0.1051,"593753":-0.0419,"758849":-0.0961,"925489":0.0,"1017223":0.3028,"1094908":null,"1127639":null,"1227370":0.0321,"1273570":0.0,"1280009":-0.9897,"1299229":0.0,"1317851":null,"1317948":null,"1354079":0.0,"1403396":0.0,"1427626":null,"1434663":0.0,"1519933":0.0,"1562247":0.0,"1583603":null,"1663371":0.2435,"1669315":0.0,"1698699":0.0,"1704576":null,"1709760":0.8528,"1751877":0.0}}