{"index":{"14076":14076,"42919":42919,"70492":70492,"76449":76449,"77545":77545,"82902":82902,"93900":93900,"93907":93907,"94292":94292,"94300":94300,"100598":100598,"101899":101899,"112996":112996,"115400":115400,"115602":115602,"118844":118844,"123348":123348,"124011":124011,"127986":127986,"133078":133078,"162431":162431,"166634":166634,"169540":169540,"189999":189999,"190031":190031,"191427":191427,"197828":197828,"203240":203240,"203790":203790,"203899":203899,"213918":213918,"228150":228150,"228388":228388,"228733":228733,"258524":258524,"263227":263227,"273176":273176,"275013":275013,"280748":280748,"281253":281253,"281340":281340,"281873":281873,"290125":290125,"291219":291219,"300821":300821,"302800":302800,"303504":303504,"306441":306441,"314989":314989,"316393":316393,"335178":335178,"341461":341461,"363886":363886,"376873":376873,"384166":384166,"391540":391540,"410502":410502,"410503":410503,"412502":412502,"423259":423259,"434549":434549,"527795":527795,"543670":543670,"568690":568690,"597231":597231,"644295":644295,"705957":705957,"764147":764147,"818408":818408,"929162":929162,"1295373":1295373,"1546350":1546350},"ticker":{"14076":"SPY","42919":"C","70492":"WMT","76449":"TLT","77545":"FCX","82902":"UAL","93900":"SLB","93907":"GDXJ","94292":"INTC","94300":"EMN","100598":"MU","101899":"BAX","112996":"ADM","115400":"FLR","115602":"W","118844":"DAL","123348":"UBER","124011":"BMY","127986":"TFC","133078":"BA","162431":"MHK","166634":"UPS","169540":"AA","189999":"FLR","190031":"NOV","191427":"DAL","197828":"ASTS","203240":"INTC","203790":"COHR","203899":"VYX","213918":"ENVX","228150":"EMN","228388":"PRGO","228733":"BCS","258524":"CLF","263227":"FTK","273176":"NXE","275013":"EVEX","280748":"DOW","281253":"PONY","281340":"SMG","281873":"BWAY","290125":"PBR","291219":"NOV","300821":"VFC","302800":"LION2","303504":"BMY","306441":"PPG","314989":"ACHR","316393":"MIR","335178":"ADNT","341461":"AOMR","363886":"DNLI","376873":"LYFT","384166":"CLF","391540":"GSM","410502":"TTI","410503":"QS","412502":"ETOR","423259":"TLS","434549":"GPRE","527795":"RUN","543670":"BORR","568690":"STIM","597231":"LUCD","644295":"DOW","705957":"SENS","764147":"SRRK","818408":"PLUG","929162":"UP","1295373":"NG","1546350":"INMB"},"investorname":{"14076":"MASTERS CAPITAL MANAGEMENT LLC","42919":"MASTERS CAPITAL MANAGEMENT LLC","70492":"MASTERS CAPITAL MANAGEMENT LLC","76449":"MASTERS CAPITAL MANAGEMENT LLC","77545":"MASTERS CAPITAL MANAGEMENT LLC","82902":"MASTERS CAPITAL MANAGEMENT LLC","93900":"MASTERS CAPITAL MANAGEMENT LLC","93907":"MASTERS CAPITAL MANAGEMENT LLC","94292":"MASTERS CAPITAL MANAGEMENT LLC","94300":"MASTERS CAPITAL MANAGEMENT LLC","100598":"MASTERS CAPITAL MANAGEMENT LLC","101899":"MASTERS CAPITAL MANAGEMENT LLC","112996":"MASTERS CAPITAL MANAGEMENT LLC","115400":"MASTERS CAPITAL MANAGEMENT LLC","115602":"MASTERS CAPITAL MANAGEMENT LLC","118844":"MASTERS CAPITAL MANAGEMENT LLC","123348":"MASTERS CAPITAL MANAGEMENT LLC","124011":"MASTERS CAPITAL MANAGEMENT LLC","127986":"MASTERS CAPITAL MANAGEMENT LLC","133078":"MASTERS CAPITAL MANAGEMENT LLC","162431":"MASTERS CAPITAL MANAGEMENT LLC","166634":"MASTERS CAPITAL MANAGEMENT LLC","169540":"MASTERS CAPITAL MANAGEMENT LLC","189999":"MASTERS CAPITAL MANAGEMENT LLC","190031":"MASTERS CAPITAL MANAGEMENT LLC","191427":"MASTERS CAPITAL MANAGEMENT LLC","197828":"MASTERS CAPITAL MANAGEMENT LLC","203240":"MASTERS CAPITAL MANAGEMENT LLC","203790":"MASTERS CAPITAL MANAGEMENT LLC","203899":"MASTERS CAPITAL MANAGEMENT LLC","213918":"MASTERS CAPITAL MANAGEMENT LLC","228150":"MASTERS CAPITAL MANAGEMENT LLC","228388":"MASTERS CAPITAL MANAGEMENT LLC","228733":"MASTERS CAPITAL MANAGEMENT LLC","258524":"MASTERS CAPITAL MANAGEMENT LLC","263227":"MASTERS CAPITAL MANAGEMENT LLC","273176":"MASTERS CAPITAL MANAGEMENT LLC","275013":"MASTERS CAPITAL MANAGEMENT LLC","280748":"MASTERS CAPITAL MANAGEMENT LLC","281253":"MASTERS CAPITAL MANAGEMENT LLC","281340":"MASTERS CAPITAL MANAGEMENT LLC","281873":"MASTERS CAPITAL MANAGEMENT LLC","290125":"MASTERS CAPITAL MANAGEMENT LLC","291219":"MASTERS CAPITAL MANAGEMENT LLC","300821":"MASTERS CAPITAL MANAGEMENT LLC","302800":"MASTERS CAPITAL MANAGEMENT LLC","303504":"MASTERS CAPITAL MANAGEMENT LLC","306441":"MASTERS CAPITAL MANAGEMENT LLC","314989":"MASTERS CAPITAL MANAGEMENT LLC","316393":"MASTERS CAPITAL MANAGEMENT LLC","335178":"MASTERS CAPITAL MANAGEMENT LLC","341461":"MASTERS CAPITAL MANAGEMENT LLC","363886":"MASTERS CAPITAL MANAGEMENT LLC","376873":"MASTERS CAPITAL MANAGEMENT LLC","384166":"MASTERS CAPITAL MANAGEMENT LLC","391540":"MASTERS CAPITAL MANAGEMENT LLC","410502":"MASTERS CAPITAL MANAGEMENT LLC","410503":"MASTERS CAPITAL MANAGEMENT LLC","412502":"MASTERS CAPITAL MANAGEMENT LLC","423259":"MASTERS CAPITAL MANAGEMENT LLC","434549":"MASTERS CAPITAL MANAGEMENT LLC","527795":"MASTERS CAPITAL MANAGEMENT LLC","543670":"MASTERS CAPITAL MANAGEMENT LLC","568690":"MASTERS CAPITAL MANAGEMENT LLC","597231":"MASTERS CAPITAL MANAGEMENT LLC","644295":"MASTERS CAPITAL MANAGEMENT LLC","705957":"MASTERS CAPITAL MANAGEMENT LLC","764147":"MASTERS CAPITAL MANAGEMENT LLC","818408":"MASTERS CAPITAL MANAGEMENT LLC","929162":"MASTERS CAPITAL MANAGEMENT LLC","1295373":"MASTERS CAPITAL MANAGEMENT LLC","1546350":"MASTERS CAPITAL MANAGEMENT LLC"},"securitytype":{"14076":"PUT","42919":"CLL","70492":"PUT","76449":"CLL","77545":"CLL","82902":"CLL","93900":"CLL","93907":"CLL","94292":"CLL","94300":"CLL","100598":"CLL","101899":"CLL","112996":"CLL","115400":"SHR","115602":"CLL","118844":"SHR","123348":"CLL","124011":"CLL","127986":"CLL","133078":"CLL","162431":"CLL","166634":"SHR","169540":"CLL","189999":"CLL","190031":"SHR","191427":"PUT","197828":"SHR","203240":"SHR","203790":"CLL","203899":"SHR","213918":"SHR","228150":"SHR","228388":"CLL","228733":"SHR","258524":"SHR","263227":"SHR","273176":"SHR","275013":"SHR","280748":"CLL","281253":"SHR","281340":"SHR","281873":"SHR","290125":"SHR","291219":"CLL","300821":"SHR","302800":"SHR","303504":"SHR","306441":"SHR","314989":"SHR","316393":"CLL","335178":"CLL","341461":"SHR","363886":"SHR","376873":"CLL","384166":"CLL","391540":"SHR","410502":"SHR","410503":"CLL","412502":"SHR","423259":"SHR","434549":"SHR","527795":"CLL","543670":"SHR","568690":"SHR","597231":"SHR","644295":"SHR","705957":"SHR","764147":"SHR","818408":"SHR","929162":"SHR","1295373":"SHR","1546350":"CLL"},"calendardate":{"14076":"2025-06-30","42919":"2025-06-30","70492":"2025-06-30","76449":"2025-06-30","77545":"2025-06-30","82902":"2025-06-30","93900":"2025-06-30","93907":"2025-06-30","94292":"2025-06-30","94300":"2025-06-30","100598":"2025-06-30","101899":"2025-06-30","112996":"2025-06-30","115400":"2025-06-30","115602":"2025-06-30","118844":"2025-06-30","123348":"2025-06-30","124011":"2025-06-30","127986":"2025-06-30","133078":"2025-06-30","162431":"2025-06-30","166634":"2025-06-30","169540":"2025-06-30","189999":"2025-06-30","190031":"2025-06-30","191427":"2025-06-30","197828":"2025-06-30","203240":"2025-06-30","203790":"2025-06-30","203899":"2025-06-30","213918":"2025-06-30","228150":"2025-06-30","228388":"2025-06-30","228733":"2025-06-30","258524":"2025-06-30","263227":"2025-06-30","273176":"2025-06-30","275013":"2025-06-30","280748":"2025-06-30","281253":"2025-06-30","281340":"2025-06-30","281873":"2025-06-30","290125":"2025-06-30","291219":"2025-06-30","300821":"2025-06-30","302800":"2025-06-30","303504":"2025-06-30","306441":"2025-06-30","314989":"2025-06-30","316393":"2025-06-30","335178":"2025-06-30","341461":"2025-06-30","363886":"2025-06-30","376873":"2025-06-30","384166":"2025-06-30","391540":"2025-06-30","410502":"2025-06-30","410503":"2025-06-30","412502":"2025-06-30","423259":"2025-06-30","434549":"2025-06-30","527795":"2025-06-30","543670":"2025-06-30","568690":"2025-06-30","597231":"2025-06-30","644295":"2025-06-30","705957":"2025-06-30","764147":"2025-06-30","818408":"2025-06-30","929162":"2025-06-30","1295373":"2025-06-30","1546350":"2025-06-30"},"value":{"14076":617850000.0,"42919":178752000.0,"70492":97780000.0,"76449":88250000.0,"77545":86700000.0,"82902":79630000.0,"93900":67600000.0,"93907":67590000.0,"94292":67200000.0,"94300":67194000.0,"100598":61625000.0,"101899":60560000.0,"112996":52780000.0,"115400":51270000.0,"115602":51140000.0,"118844":49180000.0,"123348":46650000.0,"124011":46290000.0,"127986":44275401.0,"133078":41906000.0,"162431":31452000.0,"166634":30282000.0,"169540":29510000.0,"189999":24865950.0,"190031":24860000.0,"191427":24590000.0,"197828":23365000.0,"203240":22400000.0,"203790":22302500.0,"203899":22287000.0,"213918":20680000.0,"228150":18665000.0,"228388":18634528.0,"228733":18590000.0,"258524":15200000.0,"263227":14760000.0,"273176":13880000.0,"275013":13720000.0,"280748":13240000.0,"281253":13200000.0,"281340":13192000.0,"281873":13150000.0,"290125":12510000.0,"291219":12430000.0,"300821":11750000.0,"302800":11620000.0,"303504":11572500.0,"306441":11375000.0,"314989":10850000.0,"316393":10765000.0,"335178":9730000.0,"341461":9420000.0,"363886":8394000.0,"376873":7880000.0,"384166":7600000.0,"391540":7340000.0,"410502":6720000.0,"410503":6720000.0,"412502":6659000.0,"423259":6340000.0,"434549":6030000.0,"527795":4090000.0,"543670":3843000.0,"568690":3490000.0,"597231":3136364.0,"644295":2648000.0,"705957":2143800.0,"764147":1771000.0,"818408":1490000.0,"929162":1070000.0,"1295373":409000.0,"1546350":231000.0},"units":{"14076":1000000.0,"42919":2100000.0,"70492":1000000.0,"76449":1000000.0,"77545":2000000.0,"82902":1000000.0,"93900":2000000.0,"93907":1000000.0,"94292":3000000.0,"94300":900000.0,"100598":500000.0,"101899":2000000.0,"112996":1000000.0,"115400":1000000.0,"115602":1000000.0,"118844":1000000.0,"123348":500000.0,"124011":1000000.0,"127986":1029900.0,"133078":200000.0,"162431":300000.0,"166634":300000.0,"169540":1000000.0,"189999":485000.0,"190031":2000000.0,"191427":500000.0,"197828":500000.0,"203240":1000000.0,"203790":250000.0,"203899":1900000.0,"213918":2000000.0,"228150":250000.0,"228388":697400.0,"228733":1000000.0,"258524":2000000.0,"263227":1000000.0,"273176":2000000.0,"275013":2000000.0,"280748":500000.0,"281253":1000000.0,"281340":200000.0,"281873":1000000.0,"290125":1000000.0,"291219":1000000.0,"300821":1000000.0,"302800":2000000.0,"303504":250000.0,"306441":100000.0,"314989":1000000.0,"316393":500000.0,"335178":500000.0,"341461":1000000.0,"363886":600000.0,"376873":500000.0,"384166":1000000.0,"391540":2000000.0,"410502":2000000.0,"410503":1000000.0,"412502":100000.0,"423259":2000000.0,"434549":1000000.0,"527795":500000.0,"543670":2100000.0,"568690":1000000.0,"597231":2727273.0,"644295":100000.0,"705957":4500000.0,"764147":50000.0,"818408":1000000.0,"929162":1000000.0,"1295373":100000.0,"1546350":100000.0},"price":{"14076":617.0,"42919":85.0,"70492":97.0,"76449":88.0,"77545":43.0,"82902":79.0,"93900":33.0,"93907":67.0,"94292":22.0,"94300":74.0,"100598":123.0,"101899":30.0,"112996":52.0,"115400":51.0,"115602":51.0,"118844":49.0,"123348":93.0,"124011":46.0,"127986":42.0,"133078":209.0,"162431":104.0,"166634":100.0,"169540":29.0,"189999":51.0,"190031":12.0,"191427":49.0,"197828":46.0,"203240":22.0,"203790":89.0,"203899":11.0,"213918":10.0,"228150":74.0,"228388":26.0,"228733":18.0,"258524":7.0,"263227":14.0,"273176":6.0,"275013":6.0,"280748":26.0,"281253":13.0,"281340":65.0,"281873":13.0,"290125":12.0,"291219":12.0,"300821":11.0,"302800":5.0,"303504":46.0,"306441":113.0,"314989":10.0,"316393":21.0,"335178":19.0,"341461":9.0,"363886":13.0,"376873":15.0,"384166":7.0,"391540":3.0,"410502":3.0,"410503":6.0,"412502":66.0,"423259":3.0,"434549":6.0,"527795":8.0,"543670":1.0,"568690":3.0,"597231":1.0,"644295":26.0,"705957":0.0,"764147":35.0,"818408":1.0,"929162":1.0,"1295373":4.0,"1546350":2.0},"date":{"14076":1751241600,"42919":1751241600,"70492":1751241600,"76449":1751241600,"77545":1751241600,"82902":1751241600,"93900":1751241600,"93907":1751241600,"94292":1751241600,"94300":1751241600,"100598":1751241600,"101899":1751241600,"112996":1751241600,"115400":1751241600,"115602":1751241600,"118844":1751241600,"123348":1751241600,"124011":1751241600,"127986":1751241600,"133078":1751241600,"162431":1751241600,"166634":1751241600,"169540":1751241600,"189999":1751241600,"190031":1751241600,"191427":1751241600,"197828":1751241600,"203240":1751241600,"203790":1751241600,"203899":1751241600,"213918":1751241600,"228150":1751241600,"228388":1751241600,"228733":1751241600,"258524":1751241600,"263227":1751241600,"273176":1751241600,"275013":1751241600,"280748":1751241600,"281253":1751241600,"281340":1751241600,"281873":1751241600,"290125":1751241600,"291219":1751241600,"300821":1751241600,"302800":1751241600,"303504":1751241600,"306441":1751241600,"314989":1751241600,"316393":1751241600,"335178":1751241600,"341461":1751241600,"363886":1751241600,"376873":1751241600,"384166":1751241600,"391540":1751241600,"410502":1751241600,"410503":1751241600,"412502":1751241600,"423259":1751241600,"434549":1751241600,"527795":1751241600,"543670":1751241600,"568690":1751241600,"597231":1751241600,"644295":1751241600,"705957":1751241600,"764147":1751241600,"818408":1751241600,"929162":1751241600,"1295373":1751241600,"1546350":1751241600},"pct":{"14076":0.2407,"42919":0.0696,"70492":0.0381,"76449":0.0344,"77545":0.0338,"82902":0.031,"93900":0.0263,"93907":0.0263,"94292":0.0262,"94300":0.0262,"100598":0.024,"101899":0.0236,"112996":0.0206,"115400":0.02,"115602":0.0199,"118844":0.0192,"123348":0.0182,"124011":0.018,"127986":0.0172,"133078":0.0163,"162431":0.0123,"166634":0.0118,"169540":0.0115,"189999":0.0097,"190031":0.0097,"191427":0.0096,"197828":0.0091,"203240":0.0087,"203790":0.0087,"203899":0.0087,"213918":0.0081,"228150":0.0073,"228388":0.0073,"228733":0.0072,"258524":0.0059,"263227":0.0057,"273176":0.0054,"275013":0.0053,"280748":0.0052,"281253":0.0051,"281340":0.0051,"281873":0.0051,"290125":0.0049,"291219":0.0048,"300821":0.0046,"302800":0.0045,"303504":0.0045,"306441":0.0044,"314989":0.0042,"316393":0.0042,"335178":0.0038,"341461":0.0037,"363886":0.0033,"376873":0.0031,"384166":0.003,"391540":0.0029,"410502":0.0026,"410503":0.0026,"412502":0.0026,"423259":0.0025,"434549":0.0023,"527795":0.0016,"543670":0.0015,"568690":0.0014,"597231":0.0012,"644295":0.001,"705957":0.0008,"764147":0.0007,"818408":0.0006,"929162":0.0004,"1295373":0.0002,"1546350":0.0001},"chg":{"14076":null,"42919":0.05,"70492":1.0,"76449":-0.6667,"77545":19.0,"82902":null,"93900":0.3333,"93907":null,"94292":2.0,"94300":2.6,"100598":-0.5,"101899":0.0,"112996":null,"115400":1.0619,"115602":1.5,"118844":1.0,"123348":0.0,"124011":-0.5,"127986":0.0299,"133078":null,"162431":null,"166634":0.5,"169540":0.0,"189999":-0.515,"190031":1.0,"191427":-0.7368,"197828":-0.1667,"203240":-0.5,"203790":-0.75,"203899":0.9,"213918":0.1765,"228150":0.25,"228388":-0.3026,"228733":-0.3333,"258524":-0.2,"263227":1.0,"273176":0.0,"275013":-0.0244,"280748":4.0,"281253":0.0,"281340":null,"281873":0.0,"290125":0.0,"291219":-0.5,"300821":-0.0909,"302800":3.0,"303504":-0.75,"306441":null,"314989":0.0,"316393":-0.5,"335178":null,"341461":-0.0909,"363886":null,"376873":null,"384166":-0.5,"391540":0.0,"410502":0.0526,"410503":0.0,"412502":null,"423259":-0.2593,"434549":0.0,"527795":-0.8333,"543670":0.0714,"568690":0.0,"597231":0.0,"644295":null,"705957":0.0,"764147":null,"818408":null,"929162":null,"1295373":null,"1546350":null}}