{"ticker":{"4444":"RUSHA","4647":"RUSHA","4648":"RUSHA","9269":"RUSHA","12101":"RUSHA","12245":"RUSHA","12246":"RUSHA"},"date":{"4444":"2025-08-22 00:00:00.000000","4647":"2025-08-22 00:00:00.000000","4648":"2025-08-22 00:00:00.000000","9269":"2025-08-12 00:00:00.000000","12101":"2025-08-04 00:00:00.000000","12245":"2025-08-04 00:00:00.000000","12246":"2025-08-04 00:00:00.000000"},"transactionvalue":{"4444":257625.0,"4647":35280.0,"4648":35280.0,"9269":276654.0,"12101":327840.0,"12245":47040.0,"12246":47040.0},"transactionshares":{"4444":-4500,"4647":4500,"4648":-4500,"9269":-4980,"12101":-6000,"12245":6000,"12246":-6000},"securitytitle":{"4444":"Class A Common Stock","4647":"Class A Common Stock","4648":"Option right to buy","9269":"Class B Common Stock","12101":"Class A Common Stock","12245":"Class A Common Stock","12246":"Option right to buy"},"transactioncode":{"4444":"S","4647":"M","4648":"M","9269":"S","12101":"S","12245":"M","12246":"M"},"securityadcode":{"4444":"ND","4647":null,"4648":"DD","9269":"ND","12101":"ND","12245":null,"12246":"DD"},"issuername":{"4444":"RUSH ENTERPRISES INC","4647":"RUSH ENTERPRISES INC","4648":"RUSH ENTERPRISES INC","9269":"RUSH ENTERPRISES INC","12101":"RUSH ENTERPRISES INC","12245":"RUSH ENTERPRISES INC","12246":"RUSH ENTERPRISES INC"},"ownername":{"4444":"GOLDSTONE MICHAEL L","4647":"GOLDSTONE MICHAEL L","4648":"GOLDSTONE MICHAEL L","9269":"WILDER JASON","12101":"MCROBERTS MICHAEL","12245":"MCROBERTS MICHAEL","12246":"MCROBERTS MICHAEL"},"officertitle":{"4444":"SVP GC and Corp. Sec.","4647":"SVP GC and Corp. Sec.","4648":"SVP GC and Corp. Sec.","9269":"Chief Operating Officer","12101":null,"12245":null,"12246":null},"isofficer":{"4444":"Y","4647":"Y","4648":"Y","9269":"Y","12101":"N","12245":"N","12246":"N"},"isdirector":{"4444":"N","4647":"N","4648":"N","9269":"N","12101":"Y","12245":"Y","12246":"Y"},"istenpercentowner":{"4444":"N","4647":"N","4648":"N","9269":"N","12101":"N","12245":"N","12246":"N"},"transactionpricepershare":{"4444":57.25,"4647":7.84,"4648":7.84,"9269":55.55,"12101":54.64,"12245":7.84,"12246":7.84}}