{"ticker":{"2807":"SMR","11610":"SMR","21650":"SMR","21695":"SMR"},"date":{"2807":"2025-08-27 00:00:00.000000","11610":"2025-08-05 00:00:00.000000","21650":"2025-06-30 00:00:00.000000","21695":"2025-06-30 00:00:00.000000"},"transactionvalue":{"2807":1090360.0,"11610":808092.0,"21650":36356.0,"21695":27494.0},"transactionshares":{"2807":-30641,"11610":-18206,"21650":919,"21695":695},"securitytitle":{"2807":"Class A Common Stock","11610":"Class A Common Stock","21650":"Class A Common Stock","21695":"Class A Common Stock"},"transactioncode":{"2807":"S","11610":"S","21650":"A","21695":"A"},"securityadcode":{"2807":"ND","11610":"ND","21650":null,"21695":null},"issuername":{"2807":"NUSCALE POWER CORP","11610":"NUSCALE POWER CORP","21650":"NUSCALE POWER CORP","21695":"NUSCALE POWER CORP"},"ownername":{"2807":"HAMADY ROBERT RAMSEY","11610":"FISHER CARL M","21650":"BOECKMANN ALAN L","21695":"KRESA KENT"},"officertitle":{"2807":"Chief Financial Officer","11610":"Chief Operating Officer","21650":null,"21695":null},"isofficer":{"2807":"Y","11610":"Y","21650":"N","21695":"N"},"isdirector":{"2807":"N","11610":"N","21650":"Y","21695":"Y"},"istenpercentowner":{"2807":"N","11610":"N","21650":"N","21695":"N"},"transactionpricepershare":{"2807":35.59,"11610":44.39,"21650":39.56,"21695":39.56}}