{"ticker":{"952":"TOL","1899":"TOL","2824":"TOL","4595":"TOL","4859":"TOL","16880":"TOL","17706":"TOL","17726":"TOL"},"date":{"952":"2025-09-02 00:00:00.000000","1899":"2025-08-29 00:00:00.000000","2824":"2025-08-27 00:00:00.000000","4595":"2025-08-22 00:00:00.000000","4859":"2025-08-21 00:00:00.000000","16880":"2025-07-16 00:00:00.000000","17706":"2025-07-14 00:00:00.000000","17726":"2025-07-14 00:00:00.000000"},"transactionvalue":{"952":346782.0,"1899":3456375.0,"2824":735662.0,"4595":70315.0,"4859":1286249.0,"16880":288325.0,"17706":92258.0,"17726":60000.0},"transactionshares":{"952":-2500,"1899":-25000,"2824":-5350,"4595":-500,"4859":-9831,"16880":-2500,"17706":-770,"17726":-500},"securitytitle":{"952":"Common Stock","1899":"Common Stock","2824":"Common Stock","4595":"Common Stock","4859":"Common Stock","16880":"Common Stock","17706":"Common Stock","17726":"Common Stock"},"transactioncode":{"952":"S","1899":"S","2824":"S","4595":"S","4859":"S","16880":"S","17706":"S","17726":"S"},"securityadcode":{"952":"ND","1899":"ND","2824":"ND","4595":"ND","4859":"ND","16880":"ND","17706":"ND","17726":"ND"},"issuername":{"952":"TOLL BROTHERS INC","1899":"TOLL BROTHERS INC","2824":"TOLL BROTHERS INC","4595":"TOLL BROTHERS INC","4859":"TOLL BROTHERS INC","16880":"TOLL BROTHERS INC","17706":"TOLL BROTHERS INC","17726":"TOLL BROTHERS INC"},"ownername":{"952":"PRITCHETT WENDELL E","1899":"YEARLEY DOUGLAS C JR","2824":"CONNOR MARTIN P","4595":"GRUBB MICHAEL J","4859":"PARAHUS ROBERT","16880":"EAST STEPHEN F","17706":"GARVEY CHRISTINE","17726":"GRUBB MICHAEL J"},"officertitle":{"952":null,"1899":"Chief Executive Officer","2824":"Chief Financial Officer","4595":"SVP  Chief Accounting Officer","4859":"President  COO","16880":null,"17706":null,"17726":"SVP  Chief Accounting Officer"},"isofficer":{"952":"N","1899":"Y","2824":"Y","4595":"Y","4859":"Y","16880":"N","17706":"N","17726":"Y"},"isdirector":{"952":"Y","1899":"Y","2824":"N","4595":"N","4859":"N","16880":"Y","17706":"Y","17726":"N"},"istenpercentowner":{"952":"N","1899":"N","2824":"N","4595":"N","4859":"N","16880":"N","17706":"N","17726":"N"},"transactionpricepershare":{"952":138.71,"1899":138.25,"2824":137.51,"4595":140.63,"4859":130.84,"16880":115.33,"17706":119.82,"17726":120.0}}